{
  "source": "stf",
  "source_api": "jurisprudencia.stf.jus.br",
  "doc_id": "sjur459839",
  "scraped_at": "2026-02-27T21:42:58Z",
  "scraper_version": "stf_scraper_v1.0",
  "data": {
    "base": "acordaos",
    "id": "sjur459839",
    "dg_unique": "sjur459839",
    "titulo": "Rcl 42613 AgR-ED",
    "ministro_facet": [
      "GILMAR MENDES"
    ],
    "procedencia_geografica_pais_sigla": "BR",
    "procedencia_geografica_uf_sigla": "AM",
    "procedencia_geografica_uf_extenso": "Amazonas",
    "procedencia_geografica_completo": "AM - AMAZONAS",
    "processo_codigo_completo": "Rcl 42613 AgR-ED",
    "processo_numero": 42613,
    "processo_classe_processual_unificada_sigla": "Rcl-AgR-ED",
    "processo_classe_processual_unificada_extenso": "EMB.DECL. NO AG.REG. NA RECLAMAÇÃO",
    "processo_classe_processual_unificada_classe_sigla": "Rcl",
    "processo_classe_processual_unificada_incidente_sigla": "AgR-ED",
    "is_questao_ordem": false,
    "is_repercussao_geral_admissibilidade": false,
    "is_repercussao_geral_merito": false,
    "is_repercussao_geral": false,
    "is_processo_antigo": false,
    "is_colac": false,
    "colac_numero": null,
    "colac_pagina": null,
    "relator_processo_nome": "GILMAR MENDES",
    "revisor_processo_nome": null,
    "relator_acordao_nome": null,
    "julgamento_data": "2022-02-21",
    "orgao_julgador": "Segunda Turma",
    "julgamento_is_sessao_virtual": null,
    "publicacao_data": "2022-04-12",
    "republicacao_data": null,
    "ementa_texto": "Embargos de declaração no agravo regimental na reclamação. 2. Direito Constitucional e Direito Administrativo. 3. Aprovação fora do número de vagas. Surgimento de novas vagas após o fim do prazo de validade do certame. Inexistência de direito subjetivo à nomeação. Tentativa de burla ao entendimento firmado na ADI 3.415. Reclamação julgada procedente. 4. Ofensa à autoridade da ADI 3.415 e da súmula vinculante. 5. Ausência de omissão, contradição, obscuridade ou erro material. 6. Embargos de declaração rejeitados.",
    "acordao_ata": "Decisão: A Turma, por unanimidade, rejeitou os embargos de declaração, nos termos do voto do Relator. Segunda Turma, Sessão Virtual de 11.2.2022 a 18.2.2022.",
    "inteiro_teor_url": "https://portal.stf.jus.br/jurisprudencia/obterInteiroTeor.asp?idDocumento=760188144",
    "acompanhamento_processual_url": "https://portal.stf.jus.br/processos/listarProcessos.asp?numeroProcesso=42613&classe=Rcl",
    "dje_url": "https://portal.stf.jus.br/servicos/dje/listarDiarioJustica.asp?tipoPesquisaDJ=AP&numero=42613&classe=Rcl",
    "partes_lista_texto": "EMBTE.(S)           : ADAUTO LUCIO MAUES NAZARETH \r\nEMBTE.(S)           : WALTER CABRAL DE VASCONCELOS FILHO \r\nEMBTE.(S)           : LIA GAZINEU FERREIRA \r\nEMBTE.(S)           : KETHLEEN ARAÚJO CALMONT \r\nEMBTE.(S)           : IZOLDA DE CASTRO E COUTO VALLE \r\nEMBTE.(S)           : HOSANA GOMES DE ANDRADE \r\nEMBTE.(S)           : GERALDO MAGELLA FIUZA E SILVA \r\nEMBTE.(S)           : FRANCISCO COUTINHO ROQUE \r\nEMBTE.(S)           : ANTONIO RODRIGUES DA SILVA \r\nEMBTE.(S)           : ANA PATRÍCIA VENTILARI CAVALHEIRO \r\nEMBTE.(S)           : ANA DENISE DE SOUZA MACHADO \r\nEMBTE.(S)           : AILTON MAGNO DA SILVA CARVALHO \r\nEMBTE.(S)           : AFONSO CELSO LOBO \r\nEMBTE.(S)           : ACACIA PACHECO DA SILVA DANTAS \r\nEMBTE.(S)           : MARIO JOSE SILVIO JUNIOR \r\nEMBTE.(S)           : MARCELO AUGUSTO FERREIRA PILAR \r\nEMBTE.(S)           : LUIZ IDELFONSO VEIGA MARTINS \r\nEMBTE.(S)           : JULIO CESAR CHAVES REBELO \r\nEMBTE.(S)           : JOSENILDES BAETA FROES \r\nEMBTE.(S)           : IZANDRA REGO CORREA \r\nEMBTE.(S)           : IRINEU LOUFARES BRANDAO JUNIOR \r\nEMBTE.(S)           : HUMBERTO LUCIO MENEZES DE VAQUERO \r\nEMBTE.(S)           : IVO DE SOUZA CUNHA \r\nEMBTE.(S)           : FABIOLA ESTHER QUEIROZ DE OLIVEIRA \r\nEMBTE.(S)           : FABIO OLIVEIRA GOMES \r\nEMBTE.(S)           : FABIO BRAULE PINTO FREIRE \r\nEMBTE.(S)           : CARLA JOSEPHINA MIRANDA BIAGGI \r\nEMBTE.(S)           : LINDA GLAUCIA DE MORAES \r\nEMBTE.(S)           : SERGIO LUIZ SILVA SANTOS \r\nEMBTE.(S)           : SAMARA FERNANDES DE AMORIM \r\nEMBTE.(S)           : RAIMUNDO PEREIRA PONTES FILHO \r\nEMBTE.(S)           : NILSON NASCIMENTO DOS SANTOS \r\nEMBTE.(S)           : TURIBIO JOSE CORREA DA COSTA \r\nEMBTE.(S)           : SAMIRA MOUSSE DE CARVALHO \r\nEMBTE.(S)           : RONNEY RIBEIRO NOGUEIRA \r\nEMBTE.(S)           : RENATO FONSECA DE CARVALHO \r\nEMBTE.(S)           : NORMANDO DA ROCHA BARBOSA \r\nEMBTE.(S)           : MARCO ANTONIO BARBOSA PEREIRA \r\nEMBTE.(S)           : TAMERA MACIEL ASSAD \r\nEMBTE.(S)           : ORLANDO DARIO GOIS DO AMARAL \r\nEMBTE.(S)           : PAULO ROBERTO SOBRAL MARTINS \r\nEMBTE.(S)           : LUCIANO TAVARES DA SILVA \r\nEMBTE.(S)           : HIPOLITO MENEZES CORDEIRO \r\nEMBTE.(S)           : CARLOS ALBERTO ALENCAR DE ANDRADE \r\nEMBTE.(S)           : ZANDRA COUCEIRO RIBEIRO \r\nADV.(A/S)           : FREDERICO CEZAR ABINADER DUTRA \r\nADV.(A/S)           : OLDENEY SÁ VALENTE E OUTRO(A/S)\r\nADV.(A/S)           : RICARDO DOS SANTOS CASTILHO \r\nEMBDO.(A/S)         : SINDICATO DOS DELEGADOS DE POLÍCIA DE CARREIRA DO AMAZONAS-SINDEPOL/AM E OUTRO(A/S)\r\nADV.(A/S)           : MARCELO JOSÉ BULHÕES MAGALHÃES \r\nINTDO.(A/S)         : TRIBUNAL DE JUSTIÇA DO ESTADO DO AMAZONAS \r\nADV.(A/S)           : SEM REPRESENTAÇÃO NOS AUTOS \r\nINTDO.(A/S)         : ESTADO DO AMAZONAS \r\nPROC.(A/S)(ES)      : PROCURADOR-GERAL DO ESTADO DO AMAZONAS \r\nINTDO.(A/S)         : MINISTÉRIO PÚBLICO DO ESTADO DO AMAZONAS \r\nPROC.(A/S)(ES)      : PROCURADOR-GERAL DE JUSTIÇA DO ESTADO DO AMAZONAS \r\nINTDO.(A/S)         : SIND DOS FUNC DA POLICIA CIVIL DO ESTADO DO AMAZONAS \r\nINTDO.(A/S)         : ASSOCIACAO DE DELEGADOS DE POLICIA DO ESTADO DO AMAZONAS \r\nADV.(A/S)           : RENNAN FARIA KRUGER THAMAY \r\nINTDO.(A/S)         : DEFENSORIA PUBLICA DO ESTADO DO AMAZONAS \r\nPROC.(A/S)(ES)      : DEFENSOR PÚBLICO-GERAL DO ESTADO DO AMAZONAS \r\nINTDO.(A/S)         : ALEXANDRE MORAES DA SILVA \r\nINTDO.(A/S)         : TEOTONIO REGO PEREIRA \r\nINTDO.(A/S)         : MÁRIO JUMBO MIRANDA AUFIERO E OUTRO(A/S)\r\nINTDO.(A/S)         : EMERSON DE ALMEIDA NEGREIROS \r\nINTDO.(A/S)         : MARCELLO MELO DO AMARAL \r\nINTDO.(A/S)         : SUELY DOS SANTOS COSTA \r\nINTDO.(A/S)         : TATIANA SILVA FEIJO \r\nADV.(A/S)           : SEM REPRESENTAÇÃO NOS AUTOS",
    "documental_publicacao_lista_texto": "PROCESSO ELETRÔNICO\nDJe-040  DIVULG 02-03-2022  PUBLIC 03-03-2022\nREPUBLICAÇÃO: DJe-071  DIVULG 11-04-2022  PUBLIC 12-04-2022",
    "documental_acordao_mesmo_sentido_lista_texto": null,
    "documental_acordao_mesmo_sentido_lista_html": null,
    "documental_acordao_mesmo_sentido_is_secundario": false,
    "documental_jurisprudencia_citada_texto": null,
    "documental_legislacao_citada_texto": [
      "LEG-FED   LEI-002875 ANO-2004\n    LEI ORDINÁRIA\n\n",
      "LEG-FED   LEI-002917 ANO-2004\n    LEI ORDINÁRIA\n\n",
      "LEG-FED   LEI-013105 ANO-2015\n    ART-01022 ART-01024 PAR-00002\n    CPC-2015 CÓDIGO DE PROCESSO CIVIL\n\n",
      "LEG-FED   SUV-000043\n    SÚMULA VINCULANTE DO SUPREMO TRIBUNAL FEDERAL - STF"
    ],
    "documental_indexacao_texto": "- VIDE EMENTA.",
    "documental_observacao_texto": "- Acórdão(s) citado(s):\n(EMBARGOS DE DECLARAÇÃO, REDISCUSSÃO, MATÉRIA)\nADI 3415 ED-segundos (TP), RE 1157318 AgR-ED (TP). \n- Veja ADI 3415 do STF.\nNúmero de páginas: 15.\nAnálise: 27/10/2022, DAP.",
    "documental_observacao_html": "- Acórdão(s) citado(s):\n(EMBARGOS DE DECLARAÇÃO, REDISCUSSÃO, MATÉRIA)\n<a onclick=\"openPopup('https://portal.stf.jus.br/jurisprudencia/obterInteiroTeor.asp?numero=3415&classe=ADI-ED-segundos')\" class=\"urls\">ADI 3415 ED-segundos</a> (TP), <a onclick=\"openPopup('https://portal.stf.jus.br/jurisprudencia/obterInteiroTeor.asp?numero=1157318&classe=RE-AgR-ED')\" class=\"urls\">RE 1157318 AgR-ED</a> (TP). \n- Veja ADI 3415 do STF.\nNúmero de páginas: 15.\nAnálise: 27/10/2022, DAP.",
    "documental_assunto_texto": null,
    "documental_doutrina_texto": null,
    "documental_tese_tipo": null,
    "documental_tese_texto": null,
    "documental_tese_tema_texto": null,
    "dg_atualizado_em": "2023-10-04T14:45:44.829195",
    "externo_seq_objeto_incidente": 6297771,
    "old_seq_colac": null,
    "old_seq_repercussao_geral": null,
    "old_seq_sjur": 459839,
    "ods_onu": []
  }
}