{
  "source": "stf",
  "source_api": "jurisprudencia.stf.jus.br",
  "doc_id": "sjur480561",
  "scraped_at": "2026-02-27T21:41:55Z",
  "scraper_version": "stf_scraper_v1.0",
  "data": {
    "base": "acordaos",
    "id": "sjur480561",
    "dg_unique": "sjur480561",
    "titulo": "ADI 5549",
    "ministro_facet": [
      "LUIZ FUX"
    ],
    "procedencia_geografica_pais_sigla": "BR",
    "procedencia_geografica_uf_sigla": "DF",
    "procedencia_geografica_uf_extenso": "Distrito Federal",
    "procedencia_geografica_completo": "DF - DISTRITO FEDERAL",
    "processo_codigo_completo": "ADI 5549",
    "processo_numero": 5549,
    "processo_classe_processual_unificada_sigla": "ADI",
    "processo_classe_processual_unificada_extenso": "AÇÃO DIRETA DE INCONSTITUCIONALIDADE",
    "processo_classe_processual_unificada_classe_sigla": "ADI",
    "processo_classe_processual_unificada_incidente_sigla": null,
    "is_questao_ordem": false,
    "is_repercussao_geral_admissibilidade": false,
    "is_repercussao_geral_merito": false,
    "is_repercussao_geral": false,
    "is_processo_antigo": false,
    "is_colac": false,
    "colac_numero": null,
    "colac_pagina": null,
    "relator_processo_nome": "LUIZ FUX",
    "revisor_processo_nome": null,
    "relator_acordao_nome": null,
    "julgamento_data": "2023-03-29",
    "orgao_julgador": "Tribunal Pleno",
    "julgamento_is_sessao_virtual": null,
    "publicacao_data": "2023-06-01",
    "republicacao_data": null,
    "ementa_texto": "EMENTA: ADMINISTRATIVO. AÇÃO DIRETA DE INCONSTITUCIONALIDADE. ARTIGOS 13, INCISOS IV E V, ALÍNEA \"E\"; E 14, INCISO III, ALÍNEA \"J\", DA LEI 10.233, DE 5 DE JUNHO DE 2001, NA REDAÇÃO CONFERIDA PELO ARTIGO 3º DA LEI 12.996, DE 18 DE JUNHO DE 2014. TRANSPORTE COLETIVO INTERESTADUAL E INTERNACIONAL DE PASSAGEIROS. DISPOSIÇÕES QUESTIONADAS QUE ALTERAM, DE PERMISSÃO PARA AUTORIZAÇÃO, O REGIME DE OUTORGA DA PRESTAÇÃO REGULAR DE SERVIÇOS DE TRANSPORTE TERRESTRE COLETIVO DE PASSAGEIROS DESVINCULADOS DA EXPLORAÇÃO DE INFRAESTRUTURA. ALEGAÇÃO DE OFENSA AOS ARTIGOS 37, CAPUT E INCISO XXI, E 175, CAPUT, DA CONSTITUIÇÃO FEDERAL. INEXISTÊNCIA. O USO DA AUTORIZAÇÃO PARA A OUTORGA DE SERVIÇOS PÚBLICOS POSSUI PREVISÃO CONSTITUCIONAL, INCLUSIVE NO QUE DIZ RESPEITO A SERVIÇOS DE TRANSPORTE INTERESTADUAL E INTERNACIONAL DE PASSAGEIROS (ARTIGO 21, INCISO XII, ALÍNEA \"C\", DA CONSTITUIÇÃO). EXIGÊNCIA CONSTITUCIONAL DE LICITAÇÃO QUE NÃO SE EXIGE DA AUTORIZAÇÃO DE SERVIÇOS PÚBLICOS. PRINCÍPIOS CONSTITUCIONAIS DA ADMINISTRAÇÃO PÚBLICA. CABE AO LEGISLADOR INFRACONSTITUCIONAL ESTABELECER A FORMA DE DELEGAÇÃO DE DETERMINADOS SERVIÇOS PÚBLICOS, ADMITINDO-SE QUE A SUA EXPLORAÇÃO, QUANDO NÃO REALIZADA DIRETAMENTE, SEJA FEITA MEDIANTE CONCESSÃO, PERMISSÃO OU AUTORIZAÇÃO. AÇÃO CONHECIDA E JULGADO IMPROCEDENTE O PEDIDO, DEVENDO O PODER EXECUTIVO E A ANTT PROCEDEREM À EDIÇÃO DE NOVOS DIPLOMAS, EM ATENÇÃO ÀS EXIGÊNCIAS DO ACÓRDÃO DO TRIBUNAL DE CONTAS DA UNIÃO E DA LEI 14.298/2022.\n\n\n\n    1. A assimetria regulatória estabelecida no artigo 21, XII, e, da Constituição Federal assegurou a possibilidade de se outorgar a prestação de transporte rodoviário interestadual e internacional de passageiros (TRIIP) por autorização de serviço público, máxime em razão da inexistência de restrições à oferta que justifiquem a oposição de barreiras à entrada de concorrentes no setor; da descentralização à agência reguladora de poderes para assegurar a observância de aspectos qualitativos inerentes à adequada prestação do serviço; e de a abertura do mercado para novos entrantes contribuir para a universalização do serviço e demais benefícios à população usuária.\n\n\n\n    2. A escolha estratégica pela descentralização operacional do setor, que se insere na esfera democraticamente reservada à deliberação política, porquanto concomitante à centralização normativa, confere maior normatividade ao comando constitucional contido no caput do artigo 174 da Constituição Federal, bem como aos princípios constitucionais que orientam à atuação da Administração Pública e a Ordem Econômica (BINENBOJM, Gustavo. Assimetria regulatória no setor de transporte coletivo de passageiros. In O Direito Administrativo na Atualidade. Org . WALD, Arnold et al São Paulo: Malheiros, 2017. p. 510).\n\n\n\n    3. As finalidades precípuas de concretização dos princípios da isonomia, da moralidade e de obtenção da proposta mais vantajosa são perseguidas pela ampla concorrência na execução do serviço público, via competição no mercado, porquanto inexistentes restrições à oferta que justifiquem a oposição de barreiras à entrada, hipótese em que a competição para o mercado (competition for the market), via licitação, criaria uma exclusividade ineficiente e ilegítima, ao restringir o acesso dos possíveis interessados.\n\n\n\n    4. A previsão constitucional de prestação do TRIIP por meio de autorização (Art. 21, XI, “e”) afasta a incidência do artigo 175 da Constituição Federal, que impõe prévio procedimento licitatório especificamente às modalidades de outorga que pressupõem a excludência em razão da contratação pela Administração com determinado particular .\n\n\n\n    5. A descentralização normativa à Agência Nacional de Transportes Terrestres de poderes para assegurar a observância de aspectos qualitativos promove a eficiência, adequação e atualidade da prestação do serviço autorizado, ao se estabelecer requisitos técnicos e de regularidade para a habilitação dos interessados, assim como a uniformidade das condições de contratação ditadas pelo Poder Público, necessariamente homogêneas e previamente divulgadas.\n\n\n\n    6. O compromisso regulatório celebrado entre setor público e as empresas prestadores do serviço, que corresponde às amarras a que se cingem as partes, não se esgota nos termos de edital do poder concedente, a que se somam a expertise e a acuidade da regulação setorial e concorrencial, em atuação coordenada em prol da segurança jurídica, economicidade dos investimentos e defesa dos usuários (COUTINHO, Diogo R. Direito e Economia Política na Regulação de Serviços Públicos . Saraiva: São Paulo, 2014. p. 91).\n\n\n\n    7. A abertura do setor de transporte rodoviário interestadual e internacional a novos entrantes amplia a concorrência em um serviço inegavelmente essencial, cuja relevância para os usuários e para o desenvolvimento nacional torna ainda mais expressivas as externalidades advindas da livre concorrência, como o incremento tecnológico, o aumento da qualidade e a redução dos custos.\n\n\n\n    8. Ex positis, o artigo 3º da Lei n. 12.996/2014, ao outorgar o serviço público de transporte rodoviário coletivo internacional e interestadual de passageiros por meio de autorização, insere-se no espaço de deliberação política delineado no artigo 21, XII, e , da Constituição, de modo que, observados os valores constitucionalmente tutelados, em especial os princípios que orientam a Administração Pública e a ordem econômica, não se reveste de inconstitucionalidade .\n\n\n\n    9. Ação direta de inconstitucionalidade conhecida e julgado improcedente o pedido, devendo o Poder Executivo e a ANTT ajustarem-se às exigências do Tribunal de Contas da União e às novas disposições trazidas pela Lei 14.298/2022.",
    "acordao_ata": "Após a leitura do relatório e a realização das sustentações orais, o julgamento foi suspenso. Falaram: pelo requerente, o Dr. Antônio Augusto Brandão de Aras, Procurador-Geral da República; pela Advocacia-Geral da União, o Dr. Leandro Peixoto Medeiros, Advogado da União; pelo amicus curiae ABRATI - Associação Brasileira das Empresas de Transporte Terrestre de Passageiros, o Dr. Alde da Costa Santos Junior; pelo amicus curiae Agência Nacional de Transportes Terrestres - ANTT, a Dra. Adriana Maia Venturini, Procuradora-Geral Federal; e, pelo amicus curiae Associação Brasileira de Mobilidade e Tecnologia - AMOBITEC, o Dr. Beto Ferreira Martins Vasconcelos. Presidência da Ministra Rosa Weber. Plenário, 15.3.2023.\r\n\n                       Decisão: Após o início do voto do Ministro Luiz Fux (Relator), o julgamento foi suspenso. Presidência da Ministra Rosa Weber. Plenário, 16.3.2023.\r\n\n                 Decisão: Após o voto do Ministro Luiz Fux (Relator), que conhecia integralmente da ação direta e julgava-a improcedente, e, em obiter dictum, entendia que o Poder Executivo e a ANTT devem providenciar as formalidades complementares introjetadas no acórdão do Tribunal de Contas da União e na Lei 14.298/2022, no que foi acompanhado pelos Ministros André Mendonça, Nunes Marques e Alexandre de Moraes; e do voto do Ministro Edson Fachin, que conhecia integralmente da ação e julgava procedente o pedido, o julgamento foi suspenso. Ausente, justificadamente, o Ministro Ricardo Lewandowski. Presidência da Ministra Rosa Weber. Plenário, 22.3.2023.\r\n\n                       Decisão: Após os votos dos Ministros Roberto Barroso, Dias Toffoli e Gilmar Mendes, que acompanhavam o voto do Ministro Luiz Fux (Relator); e do voto do Ministro Ricardo Lewandowski, que acompanhava a divergência aberta pelo Ministro Edson Fachin, o julgamento foi suspenso. Ausente, justificadamente, a Ministra Cármen Lúcia. Presidência da Ministra Rosa Weber. Plenário, 23.3.2023.\r\n\n                 Decisão: O Tribunal, por maioria, conheceu integralmente da ação direta e julgou-a improcedente, e, em obiter dictum, entendeu que o Poder Executivo e a ANTT devem providenciar as formalidades complementares introjetadas no acórdão do Tribunal de Contas da União e na Lei 14.298/2022, nos termos do voto do Relator, vencidos parcialmente os Ministros Edson Fachin, Ricardo Lewandowski, Cármen Lúcia e Rosa Weber (Presidente), que acompanhavam o Relator quanto ao conhecimento, mas julgavam procedente o pedido. Plenário, 29.3.2023.",
    "inteiro_teor_url": "https://portal.stf.jus.br/jurisprudencia/obterInteiroTeor.asp?idDocumento=768157260",
    "acompanhamento_processual_url": "https://portal.stf.jus.br/processos/listarProcessos.asp?numeroProcesso=5549&classe=ADI",
    "dje_url": "https://portal.stf.jus.br/servicos/dje/listarDiarioJustica.asp?tipoPesquisaDJ=AP&numero=5549&classe=ADI",
    "partes_lista_texto": "REQTE.(S)  : PROCURADOR-GERAL DA REPÚBLICA \nINTDO.(A/S)  : PRESIDENTE DA REPÚBLICA \nPROC.(A/S)(ES) : ADVOGADO-GERAL DA UNIÃO \nINTDO.(A/S)  : CONGRESSO NACIONAL \nPROC.(A/S)(ES) : ADVOGADO-GERAL DA UNIÃO \nAM. CURIAE.  : ABRATI - ASSOCIAÇÃO BRASILEIRA DAS EMPRESAS DE TRANSPORTE TERRESRE DE PASSAGEIROS \nADV.(A/S)  : ALDE DA COSTA SANTOS JUNIOR \nAM. CURIAE.  : ASSOCIAÇÃO PAULISTA DE DIREITO ADMINISTRATIVO - APDA \nADV.(A/S)  : AMAURI FERES SAAD \nADV.(A/S)  : YAHN RAINER GNECCO MARINHO DA COSTA \nADV.(A/S)  : MAURÍCIO PEREIRA COLONNA ROMANO \nAM. CURIAE.  : AGÊNCIA NACIONAL DE TRANSPORTES TERRESTRES - ANTT \nPROC.(A/S)(ES) : PROCURADOR-GERAL FEDERAL \nAM. CURIAE.  : ASSOCIAÇÃO BRASILEIRA DE MOBILIDADE E TECNOLOGIA - AMOBITEC \nADV.(A/S)  : BETO FERREIRA MARTINS VASCONCELOS \nADV.(A/S)  : FELIPE DE PAULA \nADV.(A/S)  : AMANDA MOREIRA KRAFT",
    "documental_publicacao_lista_texto": "PROCESSO ELETRÔNICO\nDJe-s/n  DIVULG 31-05-2023  PUBLIC 01-06-2023",
    "documental_acordao_mesmo_sentido_lista_texto": "ADI 6270  PROCESSO ELETRÔNICO\n          DJe-s/n  DIVULG 31-05-2023  PUBLIC 01-06-2023\n          JULG-29-03-2023  UF-DF  TURMA-TP  MIN-LUIZ FUX N.PÁG-299\n          DJe-s/n  DIVULG 31-05-2023  PUBLIC 01-06-2023",
    "documental_acordao_mesmo_sentido_lista_html": "<a onclick=\"openPopup('https://portal.stf.jus.br/jurisprudencia/obterInteiroTeor.asp?numero=6270&classe=ADI')\" class=\"urls\">ADI 6270</a>  PROCESSO ELETRÔNICO\n          DJe-s/n  DIVULG 31-05-2023  PUBLIC 01-06-2023\n          JULG-29-03-2023  UF-DF  TURMA-TP  MIN-LUIZ FUX N.PÁG-299\n          DJe-s/n  DIVULG 31-05-2023  PUBLIC 01-06-2023",
    "documental_acordao_mesmo_sentido_is_secundario": false,
    "documental_jurisprudencia_citada_texto": null,
    "documental_legislacao_citada_texto": [
      "LEG-FED   CF ANO-1967\n    ART-00005 INC-00008 ART-00008 INC-00015\n    LET-D\n    CF-1967 CONSTITUIÇÃO FEDERAL\n\n",
      "LEG-FED   EMC-000001 ANO-1969\n    EMENDA CONSTITUCIONAL\n\n",
      "LEG-FED   CF ANO-1988\n    ART-00003 INC-00001 ART-00004 PAR-ÚNICO\n    ART-00005 ART-00021 INC-00011 INC-00012\n    LET-A LET-B LET-C LET-D\n    LET-E LET-F ART-00022 INC-00009\n    ART-00030 INC-00005 ART-00037 \"CAPUT\"\n    INC-00021 ART-00059 ART-00084 \"CAPUT\"\n    INC-00004 INC-00006 INC-00012 ART-00170\n    ART-00173 ART-00174 \"CAPUT\" ART-00175\n    \"CAPUT\" PAR-ÚNICO INC-00001 INC-00002\n    INC-00003 INC-00004 ART-00178\n    CF-1988 CONSTITUIÇÃO FEDERAL\n\n",
      "LEG-FED   EMC-000019 ANO-1998\n    EMENDA CONSTITUCIONAL\n\n",
      "LEG-FED   LEI-007565 ANO-1986\n    LEI ORDINÁRIA\n\n",
      "LEG-FED   LEI-008666 ANO-1993\n    ART-00122\n    LLC-1993 LEI DE LICITAÇÕES\n\n",
      "LEG-FED   LEI-009074 ANO-1995\n    LEI ORDINÁRIA\n\n",
      "LEG-FED   LEI-009472 ANO-1997\n    ART-00131\n    LEI ORDINÁRIA\n\n",
      "LEG-FED   LEI-009491 ANO-1997\n    ART-00002 INC-00003\n    LEI ORDINÁRIA\n\n",
      "LEG-FED   LEI-009784 ANO-1999\n    LPA-1999 LEI DE PROCESSO ADMINISTRATIVO\n\n",
      "LEG-FED   LEI-009868 ANO-1999\n    ART-00012\n    LEI ORDINÁRIA\n\n",
      "LEG-FED   LEI-010233 ANO-2001\n    ART-00011 INC-00001 INC-00002 INC-00003\n    INC-00004 INC-00005 INC-00006 INC-00007\n    INC-00008 INC-00009 INC-00010 INC-00011\n    INC-00012 ART-00012 INC-00001 INC-00002\n    INC-00003 INC-00004 INC-00005 INC-00006\n    INC-00007 INC-00008 INC-00009 INC-00010\n    ART-00013 INC-00001 INC-00002 INC-00003\n    INC-00004 INC-00005 LET-E ART-00014\n    INC-00001 LET-A LET-B INC-00003\n    LET-B LET-C LET-E LET-F\n    LET-I LET-J INC-00004 LET-A\n    LET-B PAR-00001 PAR-00002 PAR-00003\n    ART-00021 INC-00012 LET-E ART-00024\n    INC-00003 ART-00026 ART-00030 ART-00043\n    INC-00002 ART-00044 INC-00004 ART-00045\n    ART-00047 ART-0047A ART-0047B PAR-ÚNICO\n    ART-0047C ART-00049 ART-00068 ART-00077\n    PAR-00003\n    LEI ORDINÁRIA\n\n",
      "LEG-FED   LEI-011182 ANO-2005\n    ART-00008 INC-00014\n    LEI ORDINÁRIA\n\n",
      "LEG-FED   LEI-012815 ANO-2013\n    LEI ORDINÁRIA\n\n",
      "LEG-FED   LEI-012996 ANO-2014\n    ART-00003 ART-00004 ART-00005\n    LEI ORDINÁRIA\n\n",
      "LEG-FED   LEI-012994 ANO-2015\n    LEI ORDINÁRIA\n\n",
      "LEG-FED   LEI-013334 ANO-2016\n    ART-00004 ART-00007 INC-00001\n    LEI ORDINÁRIA\n\n",
      "LEG-FED   LEI-013460 ANO-2017\n    ART-00006 INC-00002\n    LEI ORDINÁRIA\n\n",
      "LEG-FED   LEI-013848 ANO-2019\n    ART-00009\n    LEI ORDINÁRIA\n\n",
      "LEG-FED   LEI-013874 ANO-2019\n    LEI ORDINÁRIA\n\n",
      "LEG-FED   LEI-014273 ANO-2021\n    LEI ORDINÁRIA\n\n",
      "LEG-FED   LEI-014288 ANO-2022\n    LEI ORDINÁRIA\n\n",
      "LEG-FED   LEI-014298 ANO-2022\n    ART-00001 ART-00003 ART-00004 ART-00005\n    LEI ORDINÁRIA\n\n",
      "LEG-FED   LEI-014301 ANO-2022\n    LEI ORDINÁRIA\n\n",
      "LEG-FED   DEL-004657 ANO-1942\n    ART-00021\n    LINDB-1942 LEI DE INTRODUÇÃO ÀS NORMAS DO DIREITO BRASILEIRO (LICC-1942 LEI DE INTRODUÇÃO AO CÓDIGO CIVIL)\n\n",
      "LEG-FED   DEL-008463 ANO-1945\n    DECRETO-LEI\n\n",
      "LEG-FED   DEL-000512 ANO-1969\n    ART-00001 LET-E\n    DECRETO-LEI\n\n",
      "LEG-FED   MPR-002217 ANO-2001\n    MEDIDA PROVISÓRIA - REEDIÇÃO Nº 3\n\n",
      "LEG-FED   MPR-000576 ANO-2012\n    MEDIDA PROVISÓRIA\n\n",
      "LEG-FED   MPR-000638 ANO-2014\n    MEDIDA PROVISÓRIA - CONVERTIDA NA LEI-12996/2014\n\n",
      "LEG-FED   DEC-068961 ANO-1971\n    DECRETO\n\n",
      "LEG-FED   DEC-090958 ANO-1985\n    DECRETO\n\n",
      "LEG-FED   DEC-092353 ANO-1986\n    ART-00011 INC-00001 INC-00002\n    DECRETO\n\n",
      "LEG-FED   DEC-096756 ANO-1988\n    DECRETO\n\n",
      "LEG-FED   DEC-099072 ANO-1990\n    DECRETO\n\n",
      "LEG-FED   DEC-000952 ANO-1993\n    DECRETO\n\n",
      "LEG-FED   DEC-002521 ANO-1998\n    DECRETO\n\n",
      "LEG-FED   DEC-022173 ANO-2001\n    DECRETO\n\n",
      "LEG-FED   DEC ANO-2008\n    DECRETO DE 16 DE JULHO DE 2008\n\n",
      "LEG-FED   DEC-008057 ANO-2013\n    ANEXO-00001 ANEXO-00002 ANEXO-00003 ART-00001\n    ART-00002 ART-00003 ART-00004\n    DECRETO\n\n",
      "LEG-FED   DEC-010157 ANO-2019\n    ART-00001 ART-00002 INC-00001 INC-00002\n    INC-00003 INC-00004 PAR-ÚNICO ART-00003\n    INC-00001 INC-00002 INC-00003 PAR-00001\n    PAR-00002 ART-00004\n    DECRETO\n\n",
      "LEG-FED   RES-000912 ANO-2007\n    RESOLUÇÃO DA AGÊNCIA NACIONAL DE TRANSPORTES AQUAVIÁRIOS - ANTAQ\n\n",
      "LEG-FED   RES-002868 ANO-2008\n    RESOLUÇÃO DA AGÊNCIA NACIONAL DE TRANSPORTES TERRESTRES - ANTT\n\n",
      "LEG-FED   RES-002869 ANO-2008\n    RESOLUÇÃO DA AGÊNCIA NACIONAL DE TRANSPORTES TERRESTRES - ANTT\n\n",
      "LEG-FED   RES-003272 ANO-2009\n    RESOLUÇÃO DA AGÊNCIA NACIONAL DE TRANSPORTES TERRESTRES - ANTT\n\n",
      "LEG-FED   RES-003320 ANO-2009\n    RESOLUÇÃO DA AGÊNCIA NACIONAL DE TRANSPORTES TERRESTRES - ANTT\n\n",
      "LEG-FED   RES-000751 ANO-2011\n    RESOLUÇÃO DA AGÊNCIA NACIONAL DE TRANSPORTES TERRESTRES - ANTT\n\n",
      "LEG-FED   RES-003654 ANO-2011\n    RESOLUÇÃO DA AGÊNCIA NACIONAL DE TRANSPORTES TERRESTRES - ANTT\n\n",
      "LEG-FED   RES-003975 ANO-2012\n    RESOLUÇÃO DA AGÊNCIA NACIONAL DE TRANSPORTES TERRESTRES - ANTT\n\n",
      "LEG-FED   RES-004499 ANO-2014\n    RESOLUÇÃO DA AGÊNCIA NACIONAL DE TRANSPORTES TERRESTRES - ANTT\n\n",
      "LEG-FED   RES-004770 ANO-2015\n    ART-00002 INC-00001 ART-00010 ART-00024\n    ART-00025 ART-00029 ART-00030 ART-00033\n    ART-00051 ART-00054 ART-00076\n    RESOLUÇÃO DA AGÊNCIA NACIONAL DE TRANSPORTES TERRESTRES - ANTT\n\n",
      "LEG-FED   RES-005072 ANO-2016\n    ART-00004 ART-00006\n    RESOLUÇÃO DA AGÊNCIA NACIONAL DE TRANSPORTES TERRESTRES - ANTT\n\n",
      "LEG-FED   RES-005629 ANO-2017\n    RESOLUÇÃO DA AGÊNCIA NACIONAL DE TRANSPORTES TERRESTRES - ANTT\n\n",
      "LEG-FED   RES-000071 ANO-2019\n    ART-00001 ART-00002 INC-00001 INC-00002\n    INC-00003 INC-00004 PAR-ÚNICO ART-00003\n    INC-00001 INC-00002 INC-00003 PAR-00001\n    PAR-00002\n    RESOLUÇÃO DO CONSELHO DO PROGRAMA DE PARCERIAS DE INVESTIMENTOS DA PRESIDÊNCIA DA REPÚBLICA - CPPI\n\n",
      "LEG-FED   RES-000955 ANO-2019\n    RESOLUÇÃO DA AGÊNCIA NACIONAL DE TRANSPORTES TERRESTRES - ANTT\n\n",
      "LEG-FED   PRT-000034 ANO-2017\n    PORTARIA DA SUPERINTENDÊNCIA DE SERVIÇOS DE TRANSPORTE RODOVIÁRIO DE PASSAGEIROS - SUPAS\n\n",
      "LEG-FED   PRT-000032 ANO-2018\n    PORTARIA DA SUPERINTENDÊNCIA DE SERVIÇOS DE TRANSPORTE RODOVIÁRIO DE PASSAGEIROS - SUPAS\n\n",
      "LEG-FED   PRT-000249 ANO-2018\n    PORTARIA DA SUPERINTENDÊNCIA DE SERVIÇOS DE TRANSPORTE RODOVIÁRIO DE PASSAGEIROS - SUPAS\n\n",
      "LEG-FED   PRT-000258 ANO-2018\n    PORTARIA DA SUPERINTENDÊNCIA DE SERVIÇOS DE TRANSPORTE RODOVIÁRIO DE PASSAGEIROS - SUPAS\n\n",
      "LEG-FED   PRT-000050 ANO-2019\n    PORTARIA DA SUPERINTENDÊNCIA DE SERVIÇOS DE TRANSPORTE RODOVIÁRIO DE PASSAGEIROS - SUPAS\n\n",
      "LEG-FED   PRT-000056 ANO-2019\n    PORTARIA DA SUPERINTENDÊNCIA DE SERVIÇOS DE TRANSPORTE RODOVIÁRIO DE PASSAGEIROS - SUPAS\n\n",
      "LEG-FED   PJL-003819 ANO-2020\n    ART-00004\n    PROJETO DE LEI\n\n",
      "LEG-FED   DLB-000224 ANO-2016\n    DELIBERAÇÃO DA AGÊNCIA NACIONAL DE TRANSPORTES TERRESTRES - ANTT\n\n",
      "LEG-FED   DLB-000239 ANO-2016\n    DELIBERAÇÃO DA AGÊNCIA NACIONAL DE TRANSPORTES TERRESTRES - ANTT\n\n",
      "LEG-FED   DLB-000279 ANO-2016\n    DELIBERAÇÃO DA AGÊNCIA NACIONAL DE TRANSPORTES TERRESTRES - ANTT\n\n",
      "LEG-FED   DLB-000280 ANO-2016\n    DELIBERAÇÃO DA AGÊNCIA NACIONAL DE TRANSPORTES TERRESTRES - ANTT\n\n",
      "LEG-FED   DLB-000115 ANO-2017\n    DELIBERAÇÃO DA AGÊNCIA NACIONAL DE TRANSPORTES TERRESTRES - ANTT\n\n",
      "LEG-FED   DLB-000134 ANO-2018\n    DELIBERAÇÃO DA AGÊNCIA NACIONAL DE TRANSPORTES TERRESTRES - ANTT\n\n",
      "LEG-FED   DLB-000853 ANO-2018\n    DELIBERAÇÃO DA AGÊNCIA NACIONAL DE TRANSPORTES TERRESTRES - ANTT\n\n",
      "LEG-FED   DLB-000059 ANO-2019\n    DELIBERAÇÃO DA AGÊNCIA NACIONAL DE TRANSPORTES TERRESTRES - ANTT\n\n",
      "LEG-FED   DLB-000677 ANO-2019\n    DELIBERAÇÃO DA AGÊNCIA NACIONAL DE TRANSPORTES TERRESTRES - ANTT\n\n",
      "LEG-FED   DLB-000955 ANO-2019\n    ART-00002 ART-00003 PAR-00001 INC-00001\n    INC-00002 PAR-00002 PAR-00003 ART-00004\n    PAR-00001 PAR-00002 PAR-00003 INC-00001\n    INC-00002 INC-00003 INC-00004 INC-00005\n    INC-00006 PAR-00004 PAR-00005 ART-00005\n    ART-00006 ART-00007 ART-00008 ART-00009\n    ART-00010 ART-00011\n    DELIBERAÇÃO DA AGÊNCIA NACIONAL DE TRANSPORTES TERRESTRES - ANTT\n\n",
      "LEG-FED   PRC-003461 ANO-2014\n    PARECER DA AGÊNCIA NACIONAL DE TRANSPORTES TERRESTRES  EM CONJUNTA COM A PROCURADORIA GERAL FEDERAL E ADVOCACIA-GERAL DA UNIÃO - ANTT/PGF/AGU"
    ],
    "documental_indexacao_texto": "- ADMISSIBILIDADE, CONTROLE ABSTRATO, CONSTITUCIONALIDADE, DELIBERAÇÃO ADMINISTRATIVA, AGÊNCIA NACIONAL DE TRANSPORTES TERRESTRES (ANTT), FUNDAMENTO, CARACTERIZAÇÃO, ATO NORMATIVO ABSTRATO. INEXISTÊNCIA, LIMITE MÁXIMO, NÚMERO, AUTORIZAÇÃO. PREVISÃO, NORMA, REALIZAÇÃO, SORTEIO, HIPÓTESE, NÚMERO, INTERESSADO, EXTRAPOLAÇÃO, NÚMERO DE VAGA. ESTUDO, FUNDAÇÃO GETÚLIO VARGAS (FGV), INDICAÇÃO, LIMITAÇÃO, MARCO REGULATÓRIO, LEI ANTERIOR. MANUTENÇÃO, SUPERVISÃO, PODER PÚBLICO, MOMENTO POSTERIOR, AUTORIZAÇÃO. PARTICIPAÇÃO, AGÊNCIA NACIONAL DE TRANSPORTES TERRESTRES (ANTT), CONSELHO ADMINISTRATIVO DE DEFESA ECONÔMICA (CADE), TRIBUNAL DE CONTAS. SIMULTANEIDADE, DESCENTRALIZAÇÃO, PRESTAÇÃO DE SERVIÇO, AUMENTO, COMPETÊNCIA,AGÊNCIA NACIONAL DE TRANSPORTES TERRESTRES (ANTT). AGÊNCIA NACIONAL DE TRANSPORTES TERRESTRES (ANTT), ASSUNÇÃO, FUNÇÃO, PODER CONCEDENTE. DISCUSSÃO, NATUREZA JURÍDICA, CONTRATO, AUTORIZAÇÃO. DISTINÇÃO, CONSUMIDOR, USUÁRIO, SERVIÇO PÚBLICO. DIREITO, USUÁRIO, SERVIÇO PÚBLICO. CONSTITUCIONALIDADE, DELIBERAÇÃO, AGÊNCIA NACIONAL DE TRANSPORTES TERRESTRES (ANTT), PROIBIÇÃO, TRANSFERÊNCIA, AUTORIZAÇÃO. CONSTITUCIONALIDADE, AGÊNCIA NACIONAL DE TRANSPORTES TERRESTRES (ANTT), REVOGAÇÃO, COMPLEXO NORMATIVO. LEI DE LIBERDADE ECONÔMICA, PREVISÃO, ABUSO DO PODER REGULATÓRIO. PREJUÍZO, EXCESSO, NORMA, REGULAÇÃO. INEXISTÊNCIA, DIREITO ADQUIRIDO, REGIME JURÍDICO. INTERPRETAÇÃO SISTEMÁTICA, CONSTITUIÇÃO FEDERAL. INADEQUAÇÃO, INVOCAÇÃO, PRINCÍPIO, OBJETIVO, SUPRESSÃO, EFETIVIDADE, NORMA CONSTITUCIONAL. LEGISLAÇÃO, PREVISÃO, MULTIPLICIDADE, REQUISITO, OUTORGA, AUTORIZAÇÃO. LIBERDADE, LEGISLADOR, ESCOLHA, FORMA, OUTORGA, SERVIÇO DE TRANSPORTE.\n\n- FUNDAMENTAÇÃO COMPLEMENTAR, MIN. ANDRÉ MENDONÇA: INADMISSIBILIDADE, AÇÃO DIRETA DE INCONSTITUCIONALIDADE, IMPUGNAÇÃO, RESOLUÇÃO, APRESENTAÇÃO, OPINIÃO, DECORRÊNCIA, ATIVIDADE, CONSULTORIA, SUJEIÇÃO, APROVAÇÃO, PRESIDENTE DA REPÚBLICA. INADMISSIBILIDADE, AÇÃO DIRETA DE INCONSTITUCIONALIDADE, IMPUGNAÇÃO, DECRETO REGULAMENTAR, NATUREZA JURÍDICA, ATO NORMATIVO SECUNDÁRIO. ADMISSIBILIDADE, CONTROLE ABSTRATO, DELIBERAÇÃO, AGÊNCIA NACIONAL DE TRANSPORTES TERRESTRES (ANTT), ALTERAÇÃO, CARÁTER GENÉRICO, REGRA, REGIME JURÍDICO, CONTRATO. INEXISTÊNCIA, EXIGÊNCIA, LICITAÇÃO, FINALIDADE, OUTORGA, PERMISSÃO, CONCESSÃO, SERVIÇO PÚBLICO, MOMENTO ANTERIOR, CONSTITUIÇÃO FEDERAL DE 1988. DIFICULDADE, REALIZAÇÃO, LICITAÇÃO, SERVIÇO, TRANSPORTE RODOVIÁRIO INTERESTADUAL E INTERNACIONAL DE PASSAGEIROS (TRIIP), MOMENTO POSTERIOR, CONSTITUIÇÃO FEDERAL DE 1988. OPÇÃO, LEGISLADOR, ALTERAÇÃO, MARCO REGULATÓRIO, FINALIDADE, REALIZAÇÃO, OUTORGA, INTERMÉDIO, AUTORIZAÇÃO. CONFIGURAÇÃO, LICITAÇÃO, OBSTÁCULO, ENTRADA, INTERESSADO, MERCADO, SERVIÇO DE TRANSPORTE. DISPOSIÇÃO EXPRESSA, CONSTITUIÇÃO FEDERAL, PREVISÃO, AUTORIZAÇÃO, FORMA, OUTORGA, SERVIÇO, TRANSPORTE RODOVIÁRIO INTERESTADUAL E INTERNACIONAL DE PASSAGEIROS (TRIIP). POSSIBILIDADE, LEGISLAÇÃO INFRACONSTITUCIONAL, CRIAÇÃO, EXCEÇÃO, REGRA CONSTITUCIONAL, LICITAÇÃO, CONTRATO, PODER PÚBLICO. NECESSIDADE, ATUALIZAÇÃO, DEFINIÇÃO JURÍDICA, AUTORIZAÇÃO, ATO VINCULADO, OBSERVÂNCIA, IMPESSOALIDADE, AUSÊNCIA, PRAZO. ENTENDIMENTO, LEGISLADOR, ADEQUAÇÃO, PRESTAÇÃO, SERVIÇO, TRANSPORTE RODOVIÁRIO INTERESTADUAL E INTERNACIONAL DE PASSAGEIROS (TRIIP), REGIME JURÍDICO, CONCORRÊNCIA. PRINCÍPIO DA ESPECIALIDADE, SOLUÇÃO, CONFLITO APARENTE DE NORMAS. FINALIDADE, LICITAÇÃO, ATENDIMENTO, PRINCÍPIO DA ISONOMIA. LICITAÇÃO, SUPOSIÇÃO, LIMITAÇÃO, QUANTIDADE, CONTRATANTE. DISPENSABILIDADE, LICITAÇÃO, HIPÓTESE, GARANTIA, ACESSO, TOTALIDADE, INTERESSADO, ATIVIDADE. LIBERDADE, LEGISLADOR ORDINÁRIO, REGULAMENTAÇÃO, LICITAÇÃO. INEXISTÊNCIA, LIMITE MÁXIMO, PRESTADOR DE SERVIÇO, SERVIÇO, TRANSPORTE RODOVIÁRIO INTERESTADUAL E INTERNACIONAL DE PASSAGEIROS (TRIIP). ESCOLHA, LEGISLADOR, AUTORIZAÇÃO, FORMA, OUTORGA, SERVIÇO PÚBLICO, HIPÓTESE, SERVIÇO DE TELECOMUNICAÇÃO, ENERGIA ELÉTRICA, PORTO, TRANSPORTE AEROVIÁRIO, FERROVIA. ESTATÍSTICA,AGÊNCIA NACIONAL DE TRANSPORTES TERRESTRES (ANTT), TRIBUNAL DE CONTAS DA UNIÃO (TCU), INDICAÇÃO, BENEFÍCIO, ALTERAÇÃO, MARCO REGULATÓRIO, SERVIÇO, TRANSPORTE RODOVIÁRIO INTERESTADUAL E INTERNACIONAL DE PASSAGEIROS (TRIIP). DELIBERAÇÃO, AGÊNCIA NACIONAL DE TRANSPORTES TERRESTRES (ANTT), PROIBIÇÃO, TRANSFERÊNCIA, OUTORGA; REVOGAÇÃO, NORMA. INOCORRÊNCIA, INOVAÇÃO. OBJETIVO, DELIBERAÇÃO, AGÊNCIA NACIONAL DE TRANSPORTES TERRESTRES (ANTT), ADEQUAÇÃO, NORMA REGULAMENTADORA, MARCO REGULATÓRIO. DEVER, PODER PÚBLICO, PRESTAÇÃO DE CONTAS, TRANSPARÊNCIA. DISTINÇÃO, DISCRICIONARIEDADE, CARÁTER TÉCNICO, CARÁTER POLÍTICO. DEVER, AGÊNCIA NACIONAL DE TRANSPORTES TERRESTRES (ANTT), UTILIZAÇÃO, CRITÉRIO, CARÁTER TÉCNICO, MOMENTO, AVALIAÇÃO, PEDIDO, AUTORIZAÇÃO.\n\n- FUNDAMENTAÇÃO COMPLEMENTAR, MIN. NUNES MARQUES: DISPOSIÇÃO EXPRESSA, CONSTITUIÇÃO FEDERAL, ADMISSÃO, AUTORIZAÇÃO, FORMA, DELEGAÇÃO, SERVIÇO, TRANSPORTE RODOVIÁRIO INTERESTADUAL E INTERNACIONAL DE PASSAGEIROS (TRIIP). AUTORIZAÇÃO, ESTÍMULO, LIVRE CONCORRÊNCIA, MERCADO. INOCORRÊNCIA, OFENSA, PRINCÍPIO DA IMPESSOALIDADE. CONFIGURAÇÃO, HIPÓTESE, INEXIGIBILIDADE, LICITAÇÃO. INEXISTÊNCIA, DISCRICIONARIEDADE, ADMINISTRAÇÃO PÚBLICA, OUTORGA, AUTORIZAÇÃO, HIPÓTESE, INTERESSADO, SATISFAÇÃO, CONDIÇÃO. EVOLUÇÃO, DOUTRINA, DEFINIÇÃO JURÍDICA, AUTORIZAÇÃO. INUTILIDADE, EMPRESA, TRANSFERÊNCIA, AUTORIZAÇÃO, MARCO REGULATÓRIO, LEI NOVA.\n\n- FUNDAMENTAÇÃO COMPLEMENTAR, MIN. ALEXANDRE DE MORAES: POSSIBILIDADE, CONTROLE ABSTRATO, CONSTITUCIONALIDADE, ATO NORMATIVO AUTÔNOMO. DEFINIÇÃO, ATO NORMATIVO, ALCANCE, DECRETO AUTÔNOMO; DECRETO PRESIDENCIAL, EXTRAPOLAÇÃO, PODER REGULAMENTAR; ATO NORMATIVO, CONSELHO NACIONAL DE JUSTIÇA (CNJ), CONSELHO NACIONAL DO MINISTÉRIO PÚBLICO (CNMP); NORMA REGIMENTAL, TRIBUNAL. INADMISSIBILIDADE, AÇÃO DIRETA DE INCONSTITUCIONALIDADE, IMPUGNAÇÃO, RESOLUÇÃO, CONSELHO ADMINISTRATIVO, SUBMISSÃO, OPINIÃO, DELIBERAÇÃO, PRESIDENTE DA REPÚBLICA. INADMISSIBILIDADE, AÇÃO DIRETA DE INCONSTITUCIONALIDADE, IMPUGNAÇÃO, DECRETO REGULAMENTAR, DELIBERAÇÃO, AGÊNCIA NACIONAL DE TRANSPORTES TERRESTRES (ANTT), FUNDAMENTO, CONFIGURAÇÃO, ATO NORMATIVO SECUNDÁRIO, CARACTERIZAÇÃO, OFENSA INDIRETA, CONSTITUIÇÃO FEDERAL. RELEVÂNCIA, LICITAÇÃO, CUMPRIMENTO, PRINCÍPIO CONSTITUCIONAL, ADMINISTRAÇÃO PÚBLICA. INDISPENSABILIDADE, LICITAÇÃO, DELEGAÇÃO, SERVIÇO DE TRANSPORTE, VIA DE REGRA. DISTINÇÃO, TRATAMENTO JURÍDICO, SERVIÇO, TRANSPORTE RODOVIÁRIO INTERESTADUAL E INTERNACIONAL DE PASSAGEIROS (TRIIP). CONSTITUIÇÃO FEDERAL, ADMISSÃO, AUTORIZAÇÃO, FORMA, DELEGAÇÃO, SERVIÇO, TRANSPORTE RODOVIÁRIO INTERESTADUAL E INTERNACIONAL DE PASSAGEIROS (TRIIP). INEXISTÊNCIA, MONOPÓLIO NATURAL, SERVIÇO, TRANSPORTE RODOVIÁRIO INTERESTADUAL E INTERNACIONAL DE PASSAGEIROS (TRIIP). INEXISTÊNCIA, DESRESPEITO, DEVER, LICITAÇÃO. CARACTERIZAÇÃO, AUTORIZAÇÃO, ATO UNILATERAL, DELEGAÇÃO. AUSÊNCIA, DISCRICIONARIEDADE, AGÊNCIA NACIONAL DE TRANSPORTES TERRESTRES (ANTT), OUTORGA, AUTORIZAÇÃO, SERVIÇO, TRANSPORTE RODOVIÁRIO INTERESTADUAL E INTERNACIONAL DE PASSAGEIROS (TRIIP).\n\n- FUNDAMENTAÇÃO COMPLEMENTAR, MIN. LUÍS ROBERTO BARROSO: ALTERAÇÃO, FORMA, PRESTAÇÃO, SERVIÇO PÚBLICO, ESTADO BRASILEIRO. CONSTITUIÇÃO FEDERAL, EXIGÊNCIA, LICITAÇÃO, FINALIDADE, DELEGAÇÃO, SERVIÇO PÚBLICO, INICIATIVA PRIVADA, VIA DE REGRA. FUNDAMENTAÇÃO, LICITAÇÃO, PRINCÍPIO DA MORALIDADE, PRINCÍPIO DA IMPESSOALIDADE, PRINCÍPIO DA ISONOMIA. DISPOSIÇÃO EXPRESSA, CONSTITUIÇÃO FEDERAL, PREVISÃO, EXCEÇÃO, LICITAÇÃO, SERVIÇO, TRANSPORTE RODOVIÁRIO INTERESTADUAL E INTERNACIONAL DE PASSAGEIROS (TRIIP). INAPLICABILIDADE, LICITAÇÃO, HIPÓTESE, AUSÊNCIA, LIMITE MÁXIMO, INTERESSADO, PRESTAÇÃO DE SERVIÇO. LICITAÇÃO, CRIAÇÃO, DIFICULDADE, ACESSO, MERCADO. OBJETIVO, LEGISLAÇÃO, COMBATE, MONOPÓLIO, SERVIÇO, TRANSPORTE RODOVIÁRIO INTERESTADUAL E INTERNACIONAL DE PASSAGEIROS (TRIIP). \n\n- FUNDAMENTAÇÃO COMPLEMENTAR, MIN. GILMAR MENDES: LEI, ALTERAÇÃO, FORMA, PRESTAÇÃO, SERVIÇO, TRANSPORTE RODOVIÁRIO INTERESTADUAL E INTERNACIONAL DE PASSAGEIROS (TRIIP), IMPLEMENTAÇÃO, REGIME JURÍDICO, AUTORIZAÇÃO, ATRIBUIÇÃO, COMPETÊNCIA, AGÊNCIA NACIONAL DE TRANSPORTES TERRESTRES (ANTT), REGULAMENTAÇÃO. LEI, MANUTENÇÃO, REGIME JURÍDICO, CONCESSÃO, HIPÓTESE, SERVIÇO, TRANSPORTE RODOVIÁRIO INTERESTADUAL E INTERNACIONAL DE PASSAGEIROS (TRIIP), EXPLORAÇÃO, INFRAESTRUTURA. CONSTITUIÇÃO FEDERAL, PREVISÃO, POSSIBILIDADE, LEGISLAÇÃO, CRIAÇÃO, EXCEÇÃO, LICITAÇÃO. CONSTITUIÇÃO FEDERAL, PREVISÃO, POSSIBILIDADE, UNIÃO FEDERAL, EXPLORAÇÃO, SERVIÇO, TRANSPORTE RODOVIÁRIO INTERESTADUAL E INTERNACIONAL DE PASSAGEIROS (TRIIP), INTERMÉDIO, AUTORIZAÇÃO. APLICAÇÃO, PRINCÍPIO DA ESPECIALIDADE, CONFLITO, NORMA CONSTITUCIONAL. COMPETÊNCIA, LEGISLADOR ORDINÁRIO, ESCOLHA, FORMA, DELEGAÇÃO, SERVIÇO, TRANSPORTE RODOVIÁRIO INTERESTADUAL E INTERNACIONAL DE PASSAGEIROS (TRIIP), INICIATIVA PRIVADA. VETO PRESIDENCIAL, PERMISSÃO, AUTORIZAÇÃO, TRANSPORTE AQUAVIÁRIO, FUNDAMENTO, INTERESSE PÚBLICO. DISTINÇÃO, REGIME JURÍDICO, AUTORIZAÇÃO, REGIME JURÍDICO, PERMISSÃO, TRANSPORTE COLETIVO, PASSAGEIRO. HISTÓRIA, EVOLUÇÃO, LEGISLAÇÃO, EXPLORAÇÃO, SERVIÇO DE TRANSPORTE. DISTINÇÃO, REGIME JURÍDICO, TRANSPORTE MUNICIPAL, TRANSPORTE INTERMUNICIPAL, REGIME JURÍDICO, TRANSPORTE RODOVIÁRIO INTERESTADUAL E INTERNACIONAL DE PASSAGEIROS (TRIIP). LIBERDADE, PARLAMENTO, SUBSTITUIÇÃO, PERMISSÃO, AUTORIZAÇÃO. DEVER, PODER PÚBLICO, REGULAÇÃO, FISCALIZAÇÃO, ATUAÇÃO, INICIATIVA PRIVADA. ALTERAÇÃO, LEGISLAÇÃO, FAVORECIMENTO, LIVRE INICIATIVA, LIVRE CONCORRÊNCIA, INOVAÇÃO; CRIAÇÃO, BENEFÍCIO, MOBILIDADE URBANA, MEIO AMBIENTE; PROTEÇÃO, CONSUMIDOR; ELIMINAÇÃO, CONCENTRAÇÃO, MERCADO. EXIGÊNCIA, IMPESSOALIDADE, OBJETIVIDADE, AUSÊNCIA, EXCLUSIVIDADE, OUTORGA, AUTORIZAÇÃO.\n\n- VOTO VENCIDO, MIN. EDSON FACHIN: DISTINÇÃO, PERMISSÃO, AUTORIZAÇÃO. CONSTITUIÇÃO FEDERAL, EXIGÊNCIA, LICITAÇÃO, HIPÓTESE, PODER PÚBLICO, CONCESSÃO, PERMISSÃO, SERVIÇO PÚBLICO. CONSTITUIÇÃO FEDERAL, EXIGÊNCIA, LICITAÇÃO, CONTRATO, PODER PÚBLICO. HISTÓRIA, EVOLUÇÃO, SERVIÇO DE TRANSPORTE COLETIVO, PASSAGEIRO, CONSTITUIÇÃO FEDERAL, LEGISLAÇÃO INFRACONSTITUCIONAL. DEVER, LEGISLADOR, OBSERVÂNCIA, CONSTITUIÇÃO FEDERAL, FINALIDADE, GARANTIA, SEGURANÇA JURÍDICA, PREVISIBILIDADE, ESTABILIDADE. JURISPRUDÊNCIA, STF, RECONHECIMENTO, OFENSA, PRINCÍPIO DA ISONOMIA, PRINCÍPIO DA MORALIDADE, AUSÊNCIA, REALIZAÇÃO, LICITAÇÃO, SERVIÇO, TRANSPORTE RODOVIÁRIO INTERESTADUAL E INTERNACIONAL DE PASSAGEIROS (TRIIP).\n\n- VOTO VENCIDO, MIN. RICARDO LEWANDOWSKI: EXIGÊNCIA, LICITAÇÃO, DECORRÊNCIA, PRINCÍPIO DA MORALIDADE. LICITAÇÃO, CONCRETIZAÇÃO, PRINCÍPIO DA ISONOMIA, PRINCÍPIO DA LIVRE CONCORRÊNCIA, PRINCÍPIO DA DEFESA DO CONSUMIDOR. JURISPRUDÊNCIA, STF, ENTENDIMENTO, EXIGÊNCIA, LICITAÇÃO, TRANSPORTE PÚBLICO. INEXISTÊNCIA, EXCEPCIONALIDADE, SERVIÇO, TRANSPORTE RODOVIÁRIO INTERESTADUAL E INTERNACIONAL DE PASSAGEIROS (TRIIP). IMPOSSIBILIDADE, OUTORGA, INTERMÉDIO, AUTORIZAÇÃO. DESCABIMENTO, DISTINGUISHING. CARÁTER PRECÁRIO, AUTORIZAÇÃO.\n\n- VOTO VENCIDO, MIN. CÁRMEN LÚCIA: CONSTITUIÇÃO FEDERAL, EXIGÊNCIA, LICITAÇÃO, FINALIDADE, CELEBRAÇÃO, CONTRATO ADMINISTRATIVO.\n\n- VOTO VENCIDO, MIN. ROSA WEBER: JURISPRUDÊNCIA, STF, EXIGÊNCIA, LICITAÇÃO, SERVIÇO, TRANSPORTE RODOVIÁRIO INTERESTADUAL E INTERNACIONAL DE PASSAGEIROS (TRIIP). UNIÃO FEDERAL, RECONHECIMENTO, INCAPACIDADE, GESTÃO, LEGALIZAÇÃO, SERVIÇO, TRANSPORTE RODOVIÁRIO INTERESTADUAL E INTERNACIONAL DE PASSAGEIROS (TRIIP). INCISO, CONSTITUIÇÃO FEDERAL, PREVISÃO, POSSIBILIDADE, UNIÃO FEDERAL, DELEGAÇÃO, SERVIÇO PÚBLICO, INTERMÉDIO, AUTORIZAÇÃO, PERMISSÃO, CONCESSÃO. NECESSIDADE, AVALIAÇÃO INDIVIDUALIZADA, APLICABILIDADE, CADA, FORMA, DELEGAÇÃO, CADA, SERVIÇO PÚBLICO.\n\n- TERMO(S) DE RESGATE: BETTER REGULATION. IMUNIDADE ANTITRUSTE. DESBUROCRATIZAÇÃO. DESREGULAÇÃO. EXPERIMENTALISMO DEMOCRÁTICO.",
    "documental_observacao_texto": "- Acórdão(s) citado(s):\n(ADI, IMPUGNAÇÃO, ATO, AUSÊNCIA, CARÁTER NORMATIVO)\nADI 5899 AgR (TP), ADI 5937 AgR (TP). \n(EXIGIBILIDADE, LICITAÇÃO, SERVIÇO, TRANSPORTE RODOVIÁRIO INTERESTADUAL E INTERNACIONAL DE PASSAGEIROS)\nMS 27516 (TP), RE 607126 AgR (1ªT), ARE 805715 AgR (2ªT), RE 626844 AgR (1ªT). \n(CONTROLE ABSTRATO, CONSTITUCIONALIDADE, ATO NORMATIVO SECUNDÁRIO)\nADI 2862 (TP), ADI 3132 (TP), ADI 4095 AgR (TP), ADI 996 MC (TP), ADI 4644 AgR (TP), ADI 4874 (TP), ADI 5086 (TP), ADI 5288 (TP), ADI 5593 AgR (TP), ADI 4120 AgR (TP), ADI 5495 AgR (TP), ADI 6111 AgR (TP), ADI 6117 AgR (TP). \n(INTERVENÇÃO DO ESTADO NA ECONOMIA, CONFORMAÇÃO LEGISLATIVA)\nADI 1923 (TP). \n(PRINCÍPIO DA ISONOMIA, LICITAÇÃO)\nADI 3070 (TP). \n(OUTORGA, SERVIÇO DE TELECOMUNICAÇÃO, INTERMÉDIO, AUTORIZAÇÃO)\nADI 1668 (TP), ADI 4923 (TP), ADI 4923 ED (TP), ADI 6482 (TP). \n(EXIGIBILIDADE, LICITAÇÃO, CONCESSÃO, SERVIÇO DE TRANSPORTE COLETIVO)\nRE 140989 (1ªT), RE 264621 (2ªT), ADI 2716 (TP), AI 637782 ED (2ªT), RE 603530 AgR (1ªT), RE 1001104 (TP), ARE 1110140 AgR (2ªT), ARE 1118647 AgR (2ªT). \n(DESNECESSIDADE, LICITAÇÃO, OUTORGA, AUTORIZAÇÃO)\nRE 214382 (2ªT), ADI 4679 (TP), ADI 4747 (TP), ADI 4756 (TP), ADI 4923 (TP). \n(AÇÃO DE CONTROLE ABSTRATO DE CONSTITUCIONALIDADE, DECRETO PRESIDENCIAL)\nADI 3664 (TP), ADI 2950 AgR (TP). \n(DISTINÇÃO, REGIME JURÍDICO, AUTORIZAÇÃO, CONCESSÃO)\nRE 20111 (1ªT). \n(DESESTATIZAÇÃO, SERVIÇO, TRANSPORTE RODOVIÁRIO INTERESTADUAL E INTERNACIONAL DE PASSAGEIROS)\nMS 27516 (TP). \n(LIBERDADE DE CONFORMAÇÃO, LEGISLADOR, REGRA, LICITAÇÃO, CONTRATO, PODER PÚBLICO)\nADI 2946 (TP), ADI 3497 (TP). \n(AÇÃO DE CONTROLE ABSTRATO DE CONSTITUCIONALIDADE, ATO NORMATIVO, CNJ, CNMP)\nADC 12 MC (TP). \n(AÇÃO DE CONTROLE ABSTRATO DE CONSTITUCIONALIDADE, REGIMENTO INTERNO, TRIBUNAL)\nADI 3544 (TP), ADI 4108 MC-REF (TP). \n(OMISSÃO, UNIÃO FEDERAL, LICITAÇÃO, SERVIÇO, TRANSPORTE RODOVIÁRIO INTERESTADUAL E INTERNACIONAL DE PASSAGEIROS)\nMS 27516 (TP), STA 73 AgR (TP). \n(TRANSPORTE INDIVIDUAL, APLICATIVO MÓVEL)\nRE 1054110 (TP). \n- Decisões monocráticas citadas:\n(EXIGIBILIDADE, LICITAÇÃO, CONCESSÃO, SERVIÇO DE TRANSPORTE COLETIVO)\nADPF 81 MC.\n(AÇÃO DE CONTROLE ABSTRATO DE CONSTITUCIONALIDADE, ATO NORMATIVO, CNJ, CNMP)\nADPF 482 MC.\n(OMISSÃO, UNIÃO FEDERAL, LICITAÇÃO, SERVIÇO, TRANSPORTE RODOVIÁRIO INTERESTADUAL E INTERNACIONAL DE PASSAGEIROS)\nSTA 73, STA 357.\n- Veja ADI 6270 do STF. \n- Veja Acórdão 230/2023 (TC 033.359/2020-2) e Acórdão 559/2021, do Tribunal de Contas da União (TCU).\n- Veja Ofício Circular n. 1384, de 2019, Nota Técnica SEI 4548/2022/COARP/GEEST/SUPAS/DIR, Nota Técnica 3387/2019/DDB/DIR e Processo Administrativo n. 50501.346390/2018-26, da Agência Nacional de Transportes Terrestres (ANTT).\n- Veja Nota Técnica n. 1/2020, da 3ª Câmara de Coordenação e Revisão (Consumidor e Ordem Econômica) do Ministério Público Federal (MPF).\n- Veja Parecer 176/2014/CONJUR-MT/CGU/AGU da Consultoria Jurídica junto ao Ministério dos Transportes.\n- Veja APAC 08700.011294/2015-12, rel. Conselheiro Paulo Burnier, DOU de 28/11/2017, do Conselho Administrativo de Defesa Econômica (CADE).\n- Veja RE 1001104 (Tema 854 de RG).\nNúmero de páginas: 280.\nAnálise: 06/11/2024, AMA.",
    "documental_observacao_html": "- Acórdão(s) citado(s):\n(ADI, IMPUGNAÇÃO, ATO, AUSÊNCIA, CARÁTER NORMATIVO)\n<a onclick=\"openPopup('https://portal.stf.jus.br/jurisprudencia/obterInteiroTeor.asp?numero=5899&classe=ADI-AgR')\" class=\"urls\">ADI 5899 AgR</a> (TP), <a onclick=\"openPopup('https://portal.stf.jus.br/jurisprudencia/obterInteiroTeor.asp?numero=5937&classe=ADI-AgR')\" class=\"urls\">ADI 5937 AgR</a> (TP). \n(EXIGIBILIDADE, LICITAÇÃO, SERVIÇO, TRANSPORTE RODOVIÁRIO INTERESTADUAL E INTERNACIONAL DE PASSAGEIROS)\n<a onclick=\"openPopup('https://portal.stf.jus.br/jurisprudencia/obterInteiroTeor.asp?numero=27516&classe=MS')\" class=\"urls\">MS 27516</a> (TP), <a onclick=\"openPopup('https://portal.stf.jus.br/jurisprudencia/obterInteiroTeor.asp?numero=607126&classe=RE-AgR')\" class=\"urls\">RE 607126 AgR</a> (1ªT), <a onclick=\"openPopup('https://portal.stf.jus.br/jurisprudencia/obterInteiroTeor.asp?numero=805715&classe=ARE-AgR')\" class=\"urls\">ARE 805715 AgR</a> (2ªT), <a onclick=\"openPopup('https://portal.stf.jus.br/jurisprudencia/obterInteiroTeor.asp?numero=626844&classe=RE-AgR')\" class=\"urls\">RE 626844 AgR</a> (1ªT). \n(CONTROLE ABSTRATO, CONSTITUCIONALIDADE, ATO NORMATIVO SECUNDÁRIO)\n<a onclick=\"openPopup('https://portal.stf.jus.br/jurisprudencia/obterInteiroTeor.asp?numero=2862&classe=ADI')\" class=\"urls\">ADI 2862</a> (TP), <a onclick=\"openPopup('https://portal.stf.jus.br/jurisprudencia/obterInteiroTeor.asp?numero=3132&classe=ADI')\" class=\"urls\">ADI 3132</a> (TP), <a onclick=\"openPopup('https://portal.stf.jus.br/jurisprudencia/obterInteiroTeor.asp?numero=4095&classe=ADI-AgR')\" class=\"urls\">ADI 4095 AgR</a> (TP), <a onclick=\"openPopup('https://portal.stf.jus.br/jurisprudencia/obterInteiroTeor.asp?numero=996&classe=ADI-MC')\" class=\"urls\">ADI 996 MC</a> (TP), <a onclick=\"openPopup('https://portal.stf.jus.br/jurisprudencia/obterInteiroTeor.asp?numero=4644&classe=ADI-AgR')\" class=\"urls\">ADI 4644 AgR</a> (TP), <a onclick=\"openPopup('https://portal.stf.jus.br/jurisprudencia/obterInteiroTeor.asp?numero=4874&classe=ADI')\" class=\"urls\">ADI 4874</a> (TP), <a onclick=\"openPopup('https://portal.stf.jus.br/jurisprudencia/obterInteiroTeor.asp?numero=5086&classe=ADI')\" class=\"urls\">ADI 5086</a> (TP), <a onclick=\"openPopup('https://portal.stf.jus.br/jurisprudencia/obterInteiroTeor.asp?numero=5288&classe=ADI')\" class=\"urls\">ADI 5288</a> (TP), <a onclick=\"openPopup('https://portal.stf.jus.br/jurisprudencia/obterInteiroTeor.asp?numero=5593&classe=ADI-AgR')\" class=\"urls\">ADI 5593 AgR</a> (TP), <a onclick=\"openPopup('https://portal.stf.jus.br/jurisprudencia/obterInteiroTeor.asp?numero=4120&classe=ADI-AgR')\" class=\"urls\">ADI 4120 AgR</a> (TP), <a onclick=\"openPopup('https://portal.stf.jus.br/jurisprudencia/obterInteiroTeor.asp?numero=5495&classe=ADI-AgR')\" class=\"urls\">ADI 5495 AgR</a> (TP), <a onclick=\"openPopup('https://portal.stf.jus.br/jurisprudencia/obterInteiroTeor.asp?numero=6111&classe=ADI-AgR')\" class=\"urls\">ADI 6111 AgR</a> (TP), <a onclick=\"openPopup('https://portal.stf.jus.br/jurisprudencia/obterInteiroTeor.asp?numero=6117&classe=ADI-AgR')\" class=\"urls\">ADI 6117 AgR</a> (TP). \n(INTERVENÇÃO DO ESTADO NA ECONOMIA, CONFORMAÇÃO LEGISLATIVA)\n<a onclick=\"openPopup('https://portal.stf.jus.br/jurisprudencia/obterInteiroTeor.asp?numero=1923&classe=ADI')\" class=\"urls\">ADI 1923</a> (TP). \n(PRINCÍPIO DA ISONOMIA, LICITAÇÃO)\n<a onclick=\"openPopup('https://portal.stf.jus.br/jurisprudencia/obterInteiroTeor.asp?numero=3070&classe=ADI')\" class=\"urls\">ADI 3070</a> (TP). \n(OUTORGA, SERVIÇO DE TELECOMUNICAÇÃO, INTERMÉDIO, AUTORIZAÇÃO)\n<a onclick=\"openPopup('https://portal.stf.jus.br/jurisprudencia/obterInteiroTeor.asp?numero=1668&classe=ADI')\" class=\"urls\">ADI 1668</a> (TP), <a onclick=\"openPopup('https://portal.stf.jus.br/jurisprudencia/obterInteiroTeor.asp?numero=4923&classe=ADI')\" class=\"urls\">ADI 4923</a> (TP), <a onclick=\"openPopup('https://portal.stf.jus.br/jurisprudencia/obterInteiroTeor.asp?numero=4923&classe=ADI-ED')\" class=\"urls\">ADI 4923 ED</a> (TP), <a onclick=\"openPopup('https://portal.stf.jus.br/jurisprudencia/obterInteiroTeor.asp?numero=6482&classe=ADI')\" class=\"urls\">ADI 6482</a> (TP). \n(EXIGIBILIDADE, LICITAÇÃO, CONCESSÃO, SERVIÇO DE TRANSPORTE COLETIVO)\n<a onclick=\"openPopup('https://portal.stf.jus.br/jurisprudencia/obterInteiroTeor.asp?numero=140989&classe=RE')\" class=\"urls\">RE 140989</a> (1ªT), <a onclick=\"openPopup('https://portal.stf.jus.br/jurisprudencia/obterInteiroTeor.asp?numero=264621&classe=RE')\" class=\"urls\">RE 264621</a> (2ªT), <a onclick=\"openPopup('https://portal.stf.jus.br/jurisprudencia/obterInteiroTeor.asp?numero=2716&classe=ADI')\" class=\"urls\">ADI 2716</a> (TP), <a onclick=\"openPopup('https://portal.stf.jus.br/jurisprudencia/obterInteiroTeor.asp?numero=637782&classe=AI-ED')\" class=\"urls\">AI 637782 ED</a> (2ªT), <a onclick=\"openPopup('https://portal.stf.jus.br/jurisprudencia/obterInteiroTeor.asp?numero=603530&classe=RE-AgR')\" class=\"urls\">RE 603530 AgR</a> (1ªT), <a onclick=\"openPopup('https://portal.stf.jus.br/jurisprudencia/obterInteiroTeor.asp?numero=1001104&classe=RE')\" class=\"urls\">RE 1001104</a> (TP), <a onclick=\"openPopup('https://portal.stf.jus.br/jurisprudencia/obterInteiroTeor.asp?numero=1110140&classe=ARE-AgR')\" class=\"urls\">ARE 1110140 AgR</a> (2ªT), <a onclick=\"openPopup('https://portal.stf.jus.br/jurisprudencia/obterInteiroTeor.asp?numero=1118647&classe=ARE-AgR')\" class=\"urls\">ARE 1118647 AgR</a> (2ªT). \n(DESNECESSIDADE, LICITAÇÃO, OUTORGA, AUTORIZAÇÃO)\n<a onclick=\"openPopup('https://portal.stf.jus.br/jurisprudencia/obterInteiroTeor.asp?numero=214382&classe=RE')\" class=\"urls\">RE 214382</a> (2ªT), <a onclick=\"openPopup('https://portal.stf.jus.br/jurisprudencia/obterInteiroTeor.asp?numero=4679&classe=ADI')\" class=\"urls\">ADI 4679</a> (TP), <a onclick=\"openPopup('https://portal.stf.jus.br/jurisprudencia/obterInteiroTeor.asp?numero=4747&classe=ADI')\" class=\"urls\">ADI 4747</a> (TP), <a onclick=\"openPopup('https://portal.stf.jus.br/jurisprudencia/obterInteiroTeor.asp?numero=4756&classe=ADI')\" class=\"urls\">ADI 4756</a> (TP), <a onclick=\"openPopup('https://portal.stf.jus.br/jurisprudencia/obterInteiroTeor.asp?numero=4923&classe=ADI')\" class=\"urls\">ADI 4923</a> (TP). \n(AÇÃO DE CONTROLE ABSTRATO DE CONSTITUCIONALIDADE, DECRETO PRESIDENCIAL)\n<a onclick=\"openPopup('https://portal.stf.jus.br/jurisprudencia/obterInteiroTeor.asp?numero=3664&classe=ADI')\" class=\"urls\">ADI 3664</a> (TP), <a onclick=\"openPopup('https://portal.stf.jus.br/jurisprudencia/obterInteiroTeor.asp?numero=2950&classe=ADI-AgR')\" class=\"urls\">ADI 2950 AgR</a> (TP). \n(DISTINÇÃO, REGIME JURÍDICO, AUTORIZAÇÃO, CONCESSÃO)\n<a onclick=\"openPopup('https://portal.stf.jus.br/jurisprudencia/obterInteiroTeor.asp?numero=20111&classe=RE')\" class=\"urls\">RE 20111</a> (1ªT). \n(DESESTATIZAÇÃO, SERVIÇO, TRANSPORTE RODOVIÁRIO INTERESTADUAL E INTERNACIONAL DE PASSAGEIROS)\n<a onclick=\"openPopup('https://portal.stf.jus.br/jurisprudencia/obterInteiroTeor.asp?numero=27516&classe=MS')\" class=\"urls\">MS 27516</a> (TP). \n(LIBERDADE DE CONFORMAÇÃO, LEGISLADOR, REGRA, LICITAÇÃO, CONTRATO, PODER PÚBLICO)\n<a onclick=\"openPopup('https://portal.stf.jus.br/jurisprudencia/obterInteiroTeor.asp?numero=2946&classe=ADI')\" class=\"urls\">ADI 2946</a> (TP), <a onclick=\"openPopup('https://portal.stf.jus.br/jurisprudencia/obterInteiroTeor.asp?numero=3497&classe=ADI')\" class=\"urls\">ADI 3497</a> (TP). \n(AÇÃO DE CONTROLE ABSTRATO DE CONSTITUCIONALIDADE, ATO NORMATIVO, CNJ, CNMP)\n<a onclick=\"openPopup('https://portal.stf.jus.br/jurisprudencia/obterInteiroTeor.asp?numero=12&classe=ADC-MC')\" class=\"urls\">ADC 12 MC</a> (TP). \n(AÇÃO DE CONTROLE ABSTRATO DE CONSTITUCIONALIDADE, REGIMENTO INTERNO, TRIBUNAL)\n<a onclick=\"openPopup('https://portal.stf.jus.br/jurisprudencia/obterInteiroTeor.asp?numero=3544&classe=ADI')\" class=\"urls\">ADI 3544</a> (TP), <a onclick=\"openPopup('https://portal.stf.jus.br/jurisprudencia/obterInteiroTeor.asp?numero=4108&classe=ADI-MC-REF')\" class=\"urls\">ADI 4108 MC-REF</a> (TP). \n(OMISSÃO, UNIÃO FEDERAL, LICITAÇÃO, SERVIÇO, TRANSPORTE RODOVIÁRIO INTERESTADUAL E INTERNACIONAL DE PASSAGEIROS)\n<a onclick=\"openPopup('https://portal.stf.jus.br/jurisprudencia/obterInteiroTeor.asp?numero=27516&classe=MS')\" class=\"urls\">MS 27516</a> (TP), <a onclick=\"openPopup('https://portal.stf.jus.br/jurisprudencia/obterInteiroTeor.asp?numero=73&classe=STA-AgR')\" class=\"urls\">STA 73 AgR</a> (TP). \n(TRANSPORTE INDIVIDUAL, APLICATIVO MÓVEL)\n<a onclick=\"openPopup('https://portal.stf.jus.br/jurisprudencia/obterInteiroTeor.asp?numero=1054110&classe=RE')\" class=\"urls\">RE 1054110</a> (TP). \n- Decisões monocráticas citadas:\n(EXIGIBILIDADE, LICITAÇÃO, CONCESSÃO, SERVIÇO DE TRANSPORTE COLETIVO)\nADPF 81 MC.\n(AÇÃO DE CONTROLE ABSTRATO DE CONSTITUCIONALIDADE, ATO NORMATIVO, CNJ, CNMP)\nADPF 482 MC.\n(OMISSÃO, UNIÃO FEDERAL, LICITAÇÃO, SERVIÇO, TRANSPORTE RODOVIÁRIO INTERESTADUAL E INTERNACIONAL DE PASSAGEIROS)\nSTA 73, STA 357.\n- Veja ADI 6270 do STF. \n- Veja Acórdão 230/2023 (TC 033.359/2020-2) e Acórdão 559/2021, do Tribunal de Contas da União (TCU).\n- Veja Ofício Circular n. 1384, de 2019, Nota Técnica SEI 4548/2022/COARP/GEEST/SUPAS/DIR, Nota Técnica 3387/2019/DDB/DIR e Processo Administrativo n. 50501.346390/2018-26, da Agência Nacional de Transportes Terrestres (ANTT).\n- Veja Nota Técnica n. 1/2020, da 3ª Câmara de Coordenação e Revisão (Consumidor e Ordem Econômica) do Ministério Público Federal (MPF).\n- Veja Parecer 176/2014/CONJUR-MT/CGU/AGU da Consultoria Jurídica junto ao Ministério dos Transportes.\n- Veja APAC 08700.011294/2015-12, rel. Conselheiro Paulo Burnier, DOU de 28/11/2017, do Conselho Administrativo de Defesa Econômica (CADE).\n- Veja RE 1001104 (Tema 854 de RG).\nNúmero de páginas: 280.\nAnálise: 06/11/2024, AMA.",
    "documental_assunto_texto": null,
    "documental_doutrina_texto": "ARAGÃO, Alexandre. Direito dos Serviços Públicos. p. 380.\nBARROSO, Luís Roberto. O Direito Constitucional e a efetividade de suas normas: limites e possibilidades da Constituição brasileira. 9. ed. Rio de Janeiro: Renovar, 2009. p. 76 e 86.\nBENTO, Wesley. Licitação no serviço de transporte rodoviário de passageiros: A inconstitucionalidade do art. 3º da lei 12.996/14. Disponível em: https://migalhas.uol.com.br/depeso/245442/licitacao-no-servico-detransporte-rodoviario-de-passageiros--a-inconstitucionalidade-do-art--3--da-lei-12-996-14. Acesso em: 17 out. 2020.\nBINENBOJM, Gustavo. Assimetria regulatória no setor de transporte coletivo de passageiros. In: WALD, Arnold et al. (org.). O Direito Administrativo na Atualidade. São Paulo: Malheiros, 2017. p. 510.\nBINENBOJM, Gustavo. Assimetria Regulatória no Setor de Transporte Coletivo Interestadual e Internacional de Passageiros: a constitucionalidade do art. 3º da Lei nº 12.996/2014. Revista de Direito da Cidade, v. 9, n. 3, p. 1268-1285, 2017.\nCARVALHO FILHO, José dos Santos. Manual de Direito Administrativo. 15. ed. Rio de Janeiro: Lumen Juris, 2006. p. 361-362.\nCASSAGNE, Juan Carlos; ORTIZ, Gaspar Ariño. Servicios Públicos, Regulación y Renegociación. Buenos Aires: Lexis Nexis, 2005. p. 104-105.\nCOUTINHO, Diogo R. Direito e Economia Política na Regulação de Serviços Públicos. Saraiva: São Paulo, 2014. p. 91.\nCRETELLA JÚNIOR, José. Fundamentos do direito administrativo. Revista da Faculdade de Direito, Universidade de São Paulo, v. 72, n. 1, 1977. p. 304.\nDI PIETRO, Maria Sílvia Zanella. Direito administrativo. 27. ed. São Paulo: Atlas. p. 238.\nFREIRE, André Luiz. O regime de direito público na prestação de serviços públicos por pessoas privadas. São Paulo: Malheiros, 2015. p. 397.\nJUSTEN FILHO, Marçal. Comentários à Lei de Licitações e Contratos Administrativos. São Paulo: Dialética, 2008. p. 46.\nJUSTEN FILHO, Marçal. Curso de Direito Administrativo. São Paulo: Revista dos Tribunais, 2013. p. 837-838 e 842.\nKELSEN, Hans. Teoria geral das normas. Porto Alegre: Fabris, 1986. p. 2-6.\nMEDAUAR, Odete. Ainda existe um serviço público? In: TORRES, Heleno. Serviços Públicos e Direito\nTributário. São Paulo: Quartier Latin, 2005. p. 38.\nMEIRELLES, Hely Lopes. Direito administrativo brasileiro. 35. ed. São Paulo: Malheiros. p. 410-411.\nMORAES, Alexandre de. Constituição do Brasil Interpretada e Legislação Constitucional. 9. ed. São Paulo: Atlas, 2013. p. 865.\nMOREIRA NETO, Diogo de Figueiredo. Curso de Direito Administrativo. Rio de Janeiro: Forense, 2014. p. 101.\nNEVES, A. Castanheira. O problema da constitucionalidade dos assentos. Coimbra: Coimbra, 1994.\nOLIVEIRA, Gustavo Justino de; FERRAZ, Pedro da Cunha. Dilemas regulatórios na prestação do serviço de transporte coletivo rodoviário interestadual e internacional de passageiros: a autorização de serviço público na Lei n.º 10.233/01 ante as inovações tecnológicas que impactam o setor de transportes. In: TOJAL, Sebastião Botto de Barros (coord.). Direito e infraestrutura: rodovias e ferrovias – 20 anos da Lei n.º 10.233/2001. Belo Horizonte: Forum, 2021, v.2. p. 103-121 e 104-105.\nPIOVESAN, Eduardo. MP regulamenta concessão de licença ao transporte interestadual. Agência Câmara de Notícias, 25 maio 2014. Disponível em: https://www.camara.leg.br/noticias/435128-mp-regulamenta-concessaode-licenca-ao-transporte-interestadual. Acesso em: 17 out. 2020.\nSCHIRATO, Vitor Rhein. Os desafios da regulação dos serviços públicos de transporte coletivo diante de novas tecnologias. In: ARAGÃO. Alexandre Santos de et al. (coord.). Regulação e Infraestrutura. Belo Horizonte: Fórum, 2018. p. 674-675.\nSUNDFELD, Carlos Ari. Licitação e Contrato Administrativo. São Paulo: Malheiros. p. 15.\nSUNSTEIN, Cass. The Truth About Trump and Deregulation. Bloomberg, 24 jun. 2017.\nUNGER, Roberto Mangabeira (2011). A constituição do experimentalismo democrático. Revista de Direito\nAdministrativo, 257. p. 57-72. Disponível em: https://doi.org/10.12660/rda.v257.2011.8584. Acesso em:\n15 mar. 2023.",
    "documental_tese_tipo": null,
    "documental_tese_texto": null,
    "documental_tese_tema_texto": null,
    "dg_atualizado_em": "2024-11-15T08:20:02.091656",
    "externo_seq_objeto_incidente": 5005055,
    "old_seq_colac": null,
    "old_seq_repercussao_geral": null,
    "old_seq_sjur": 480561,
    "ods_onu": [
      "8",
      "9",
      "11",
      "17"
    ]
  }
}