{
  "source": "stf",
  "source_api": "jurisprudencia.stf.jus.br",
  "doc_id": "sjur444522",
  "scraped_at": "2026-02-27T21:55:38Z",
  "scraper_version": "stf_scraper_v1.0",
  "data": {
    "base": "acordaos",
    "id": "sjur444522",
    "dg_unique": "sjur444522",
    "titulo": "Rcl 41765 AgR",
    "ministro_facet": [
      "ROSA WEBER",
      "DIAS TOFFOLI"
    ],
    "procedencia_geografica_pais_sigla": "BR",
    "procedencia_geografica_uf_sigla": "DF",
    "procedencia_geografica_uf_extenso": "Distrito Federal",
    "procedencia_geografica_completo": "DF - DISTRITO FEDERAL",
    "processo_codigo_completo": "Rcl 41765 AgR",
    "processo_numero": 41765,
    "processo_classe_processual_unificada_sigla": "Rcl-AgR",
    "processo_classe_processual_unificada_extenso": "AG.REG. NA RECLAMAÇÃO",
    "processo_classe_processual_unificada_classe_sigla": "Rcl",
    "processo_classe_processual_unificada_incidente_sigla": "AgR",
    "is_questao_ordem": false,
    "is_repercussao_geral_admissibilidade": false,
    "is_repercussao_geral_merito": false,
    "is_repercussao_geral": false,
    "is_processo_antigo": false,
    "is_colac": false,
    "colac_numero": null,
    "colac_pagina": null,
    "relator_processo_nome": "ROSA WEBER",
    "revisor_processo_nome": null,
    "relator_acordao_nome": "DIAS TOFFOLI",
    "julgamento_data": "2021-02-17",
    "orgao_julgador": "Primeira Turma",
    "julgamento_is_sessao_virtual": null,
    "publicacao_data": "2021-04-20",
    "republicacao_data": null,
    "ementa_texto": "EMENTA\n\n\n\n    Agravo regimental na reclamação. Negativa de seguimento de recurso da competência do TST com fundamento na Súmula nº 126/TST e na ausência do requisito do art. 896, § 1º-A, I, da CLT. Prevalência do princípio da primazia da solução de mérito (art. 4º do CPC). Desrespeito à autoridade do Supremo Tribunal Federal (STF) quanto ao que foi firmado no Tema 246 da repercussão geral. Dever da Corte de origem de se manifestar fundamentadamente sobre a aplicação da tese firmada pelo STF. Agravo regimental provido e reclamação julgada procedente para determinar ao TST que dê regular trâmite ao recurso de sua competência e a seus consectários, analisando o processo à luz do entendimento formado no Tema 246 RG.\n\n\n\n    1. Não obstante o princípio da especialidade recomende a incidência da CLT no processo trabalhista, é certo que a sistemática da repercussão geral tem sua regulamentação no CPC e deve ser aplicada de maneira isonômica entre os órgãos do Poder Judiciário nacional, por regulamentar a competência do STF para solucionar, como última instância, matéria constitucional dotada de repercussão geral, competindo aos demais órgãos do Poder Judiciário a concretização da tese caso a caso.\n\n\n\n    2. Considerando que, na Justiça Especializada, o trâmite do processo na Corte Superior é instância necessária para viabilizar o acesso ao Supremo Tribunal Federal de processo em que se debata temática resolvida pela sistemática da repercussão geral por esse Tribunal, o formalismo do art. 896, § 1º-A, I, da CLT deve ser afastado, bem como o alegado óbice da Súmula 126/TST, tendo o TST o dever de se manifestar fundamentadamente sobre a aplicação da tese firmada pelo STF, sob pena de se caracterizar, ipso facto, desrespeito à autoridade desse Tribunal.\n\n\n\n    3. Agravo regimental provido e reclamação julgada procedente para para determinar ao TST que dê regular trâmite ao recurso de sua competência e a seus consectários, analisando o processo à luz do entendimento formado no Tema 246 RG, cuja tese é a seguinte: “O inadimplemento dos encargos trabalhistas dos empregados do contratado não transfere automaticamente ao Poder Público contratante a responsabilidade pelo seu pagamento, seja em caráter solidário ou subsidiário, nos termos do art. 71, § 1º, da Lei nº 8.666/93”.",
    "acordao_ata": "A Turma, nos termos do voto médio do Ministro Dias Toffoli, Presidente, deu provimento ao agravo para julgar procedente a reclamação em menor extensão, cassando a decisão reclamada e determinando ao TST que dê regular trâmite ao recurso de sua competência e seus consectários para analisar o processo à luz do entendimento formado no Tema 246 RG, com a seguinte tese: “O inadimplemento dos encargos trabalhistas dos empregados do contratado não transfere automaticamente ao Poder Público contratante a responsabilidade pelo seu pagamento, seja em caráter solidário ou subsidiário, nos termos do art. 71, § 1º, da Lei nº 8.666/93.” A Ministra Rosa Weber (Relatora) e o Ministro Marco Aurélio negavam provimento ao agravo. Os Ministros Alexandre de Moraes e Luís Roberto Barroso davam provimento ao agravo para julgar procedente o pedido, cassando o acórdão reclamado na parte em que atribui responsabilidade subsidiária à parte agravante. Redigirá o acórdão o Ministro Dias Toffoli (Presidente). Primeira Turma, Sessão Virtual de 5.2.2021 a 12.2.2021. Primeira Turma, Sessão Virtual de 5.2.2021 a 12.2.2021.\r\n\n           Decisão: A Turma, nos termos do voto médio do Ministro Dias Toffoli, Presidente, deu provimento ao agravo para julgar procedente a reclamação em menor extensão, cassando a decisão reclamada e determinando ao TST que dê regular trâmite ao recurso de sua competência e seus consectários para analisar o processo à luz do entendimento formado no Tema 246 RG, com a seguinte tese: “O inadimplemento dos encargos trabalhistas dos empregados do contratado não transfere automaticamente ao Poder Público contratante a responsabilidade pelo seu pagamento, seja em caráter solidário ou subsidiário, nos termos do art. 71, § 1º, da Lei nº 8.666/93.” A Ministra Rosa Weber (Relatora) e o Ministro Marco Aurélio negavam provimento ao agravo. Os Ministros Alexandre de Moraes e Luís Roberto Barroso davam provimento ao agravo para julgar procedente o pedido, cassando o acórdão reclamado na parte em que atribui responsabilidade subsidiária à parte agravante. Redigirá o acórdão o Ministro Dias Toffoli (Presidente). Primeira Turma, Sessão Virtual de 5.2.2021 a 12.2.2021.",
    "inteiro_teor_url": "https://portal.stf.jus.br/jurisprudencia/obterInteiroTeor.asp?idDocumento=755630264",
    "acompanhamento_processual_url": "https://portal.stf.jus.br/processos/listarProcessos.asp?numeroProcesso=41765&classe=Rcl",
    "dje_url": "https://portal.stf.jus.br/servicos/dje/listarDiarioJustica.asp?tipoPesquisaDJ=AP&numero=41765&classe=Rcl",
    "partes_lista_texto": "AGTE.(S)  : BANCO DO BRASIL SA \nADV.(A/S)  : PRISCILLA HORTA DO NASCIMENTO \nAGDO.(A/S)  : MARCIO TENENTE XAVIER \nADV.(A/S)  : SEM REPRESENTAÇÃO NOS AUTOS \nINTDO.(A/S)  : RELATORES DOS AIRR Nº 10921-30.2015.5.01.0522, 10191-65.2014.5.01.0421, 11509-40.2016.5.03.0136, 10053-43.2016.5.15.0032 E 101264-97.2016.5.01.0082 DO TRIBUNAL SUPERIOR DO TRABALHO \nADV.(A/S)  : SEM REPRESENTAÇÃO NOS AUTOS",
    "documental_publicacao_lista_texto": "PROCESSO ELETRÔNICO\nDJe-074  DIVULG 19-04-2021  PUBLIC 20-04-2021",
    "documental_acordao_mesmo_sentido_lista_texto": null,
    "documental_acordao_mesmo_sentido_lista_html": null,
    "documental_acordao_mesmo_sentido_is_secundario": false,
    "documental_jurisprudencia_citada_texto": null,
    "documental_legislacao_citada_texto": [
      "LEG-FED   LEI-008666 ANO-1993\n    ART-00071 PAR-00001\n    LLC-1993 LEI DE LICITAÇÕES\n\n",
      "LEG-FED   LEI-013105 ANO-2015\n    ART-00004 ART-00322 PAR-00002\n    CPC-2015 CÓDIGO DE PROCESSO CIVIL\n\n",
      "LEG-FED   DEL-005452 ANO-1943\n    ART-00896 PAR-0001A INC-00001\n    CLT-1943 CONSOLIDAÇÃO DAS LEIS DO TRABALHO\n\n",
      "LEG-FED   SUMTST-000126\n    SÚMULA DO TRIBUNAL SUPERIOR DO TRABALHO - TST\n\n",
      "LEG-FED   SUMTST-000331\n    ITEM-00005 ITEM-00006\n    SÚMULA DO TRIBUNAL SUPERIOR DO TRABALHO - TST"
    ],
    "documental_indexacao_texto": "- EXIGÊNCIA, ESGOTAMENTO, INSTÂNCIA , APRECIAÇÃO, MÉRITO, STF.\n\n- FUNDAMENTAÇÃO COMPLEMENTAR, MIN. ALEXANDRE DE MORAES: RECLAMAÇÃO, AUSÊNCIA, PREENCHIMENTO, PRESSUPOSTO PROCESSUAL, RECURSO, TRIBUNAL DE ORIGEM. AUSÊNCIA, EXIGÊNCIA, ESGOTAMENTO, INSTÂNCIA ORDINÁRIA. PRIORIDADE, DECISÃO DE MÉRITO, PRINCÍPIO DA SEGURANÇA JURÍDICA, EFETIVIDADE, PRESTAÇÃO JURISDICIONAL, INTERPRETAÇÃO SISTEMÁTICA, PEDIDO. PLENÁRIO, STF, INEXISTÊNCIA, RESPONSABILIDADE, ADMINISTRAÇÃO PÚBLICA, DÉBITO TRABALHISTA, TERCEIRO, INVERSÃO DO ÔNUS DA PROVA, FAVORECIMENTO, TRABALHADOR. AUSÊNCIA, COMPROVAÇÃO, NEGLIGÊNCIA, ADMINISTRAÇÃO PÚBLICA, REFERÊNCIA, EMPREGADO TERCEIRIZADO. AUSÊNCIA, PROVA, NEXO DE CAUSALIDADE, ATO COMISSIVO, ATO OMISSIVO, PODER PÚBLICO, DANO, TRABALHADOR.\n\n- VOTO VENCIDO, MIN. ROSA WEBER: JULGAMENTO, TRIBUNAL SUPERIOR DO TRABALHO (TST), INEXISTÊNCIA, REQUISITO, TRANSCENDÊNCIA, AUSÊNCIA, DISSÍDIO JURISPRUDENCIAL. AUSÊNCIA, USURPAÇÃO DE COMPETÊNCIA. CABIMENTO, RESPONSABILIDADE SUBSIDIÁRIA, ENTE PÚBLICO, CONDUTA CULPOSA, ADMINISTRAÇÃO PÚBLICA. AUSÊNCIA, OFENSA, AÇÃO DECLARATÓRIA DE CONSTITUCIONALIDADE, OMISSÃO, ADMINISTRAÇÃO PÚBLICA, FISCALIZAÇÃO, OBRIGAÇÃO TRABALHISTA, CULPA IN VIGILANDO. IMPOSSIBILIDADE, RESPONSABILIDADE SUBSIDIÁRIA, FORMA AUTOMÁTICA, ADMINISTRAÇÃO PÚBLICA, DECORRÊNCIA, INADIMPLEMENTO, EMPRESA PRESTADORA DE SERVIÇO. AUSÊNCIA, APRECIAÇÃO, DISTRIBUIÇÃO, ÔNUS DA PROVA, JULGAMENTO, PLENÁRIO, STF. INVIABILIDADE, RECLAMAÇÃO, REEXAME, FATO, PROVA.",
    "documental_observacao_texto": "- Acórdão(s) citado(s):\n(RECLAMAÇÃO, PRESSUPOSTO DE ADMISSIBILIDADE, RECURSO DE REVISTA, USURPAÇÃO DE COMPETÊNCIA)\nRcl 38404 AgR (1ªT), Rcl 39505 AgR (2ªT), Rcl 39660 AgR (2ªT), Rcl 36811 AgR (1ªT). \n(RESPONSABILIDADE SUBSIDIÁRIA, ADMINISTRAÇÃO PÚBLICA, INADIMPLEMENTO, EMPRESA PRESTADORA DE SERVIÇO, DISTRIBUIÇÃO, ÔNUS DA PROVA)\nRE 760931 ED-terceiros (TP). \n(RECLAMAÇÃO, REEXAME, FATO, PROVA)\nRcl 12623 AgR-segundo (1ªT), Rcl 19845 AgR (1ªT), Rcl 20895 AgR (2ªT), Rcl 22129 AgR (1ªT), Rcl 27554 AgR (2ªT), Rcl 30882 AgR (2ªT), Rcl 30880 AgR (2ªT), Rcl 33578 AgR (2ªT). \n(COMPROVAÇÃO, NEGLIGÊNCIA, ADMINISTRAÇÃO PÚBLICA, EMPREGADO TERCEIRIZADO, PROVA, NEXO DE CAUSALIDADE, CONDUTA, DANO, TRABALHADOR)\nRcl 30560 AgR (1ªT), Rcl 34039 AgR (1ªT), Rcl 38016 AgR (1ªT), Rcl 36836 ED-AgR (1ªT), Rcl 39844 AgR (1ªT), Rcl 39978 AgR (1ªT). \n- Decisões monocráticas citadas:\n(RESPONSABILIDADE SUBSIDIÁRIA, ADMINISTRAÇÃO PÚBLICA, INADIMPLEMENTO, EMPRESA PRESTADORA DE SERVIÇO, DISTRIBUIÇÃO, ÔNUS DA PROVA)\nRcl 14832 MC, Rcl 15385 MC, Rcl 15194.\n(RECLAMAÇÃO, REEXAME, FATO, PROVA)\nRcl 14048, Rcl 12634, Rcl 17831, Rcl 21162, Rcl 21495.\n(INTERPRETAÇÃO SISTEMÁTICA, PEDIDO)\nRcl 37203, Rcl 37298, Rcl 41513.\n(COMPROVAÇÃO, NEGLIGÊNCIA, ADMINISTRAÇÃO PÚBLICA, EMPREGADO TERCEIRIZADO, PROVA, NEXO DE CAUSALIDADE, CONDUTA, DANO, TRABALHADOR)\nRcl 37320.\n- Veja ADC 16 e RE 760931 do STF.\nNúmero de páginas: 28.\nAnálise: 02/03/2022, JSF.",
    "documental_observacao_html": "- Acórdão(s) citado(s):\n(RECLAMAÇÃO, PRESSUPOSTO DE ADMISSIBILIDADE, RECURSO DE REVISTA, USURPAÇÃO DE COMPETÊNCIA)\n<a onclick=\"openPopup('https://portal.stf.jus.br/jurisprudencia/obterInteiroTeor.asp?numero=38404&classe=Rcl-AgR')\" class=\"urls\">Rcl 38404 AgR</a> (1ªT), <a onclick=\"openPopup('https://portal.stf.jus.br/jurisprudencia/obterInteiroTeor.asp?numero=39505&classe=Rcl-AgR')\" class=\"urls\">Rcl 39505 AgR</a> (2ªT), <a onclick=\"openPopup('https://portal.stf.jus.br/jurisprudencia/obterInteiroTeor.asp?numero=39660&classe=Rcl-AgR')\" class=\"urls\">Rcl 39660 AgR</a> (2ªT), <a onclick=\"openPopup('https://portal.stf.jus.br/jurisprudencia/obterInteiroTeor.asp?numero=36811&classe=Rcl-AgR')\" class=\"urls\">Rcl 36811 AgR</a> (1ªT). \n(RESPONSABILIDADE SUBSIDIÁRIA, ADMINISTRAÇÃO PÚBLICA, INADIMPLEMENTO, EMPRESA PRESTADORA DE SERVIÇO, DISTRIBUIÇÃO, ÔNUS DA PROVA)\n<a onclick=\"openPopup('https://portal.stf.jus.br/jurisprudencia/obterInteiroTeor.asp?numero=760931&classe=RE-ED-terceiros')\" class=\"urls\">RE 760931 ED-terceiros</a> (TP). \n(RECLAMAÇÃO, REEXAME, FATO, PROVA)\n<a onclick=\"openPopup('https://portal.stf.jus.br/jurisprudencia/obterInteiroTeor.asp?numero=12623&classe=Rcl-AgR-segundo')\" class=\"urls\">Rcl 12623 AgR-segundo</a> (1ªT), <a onclick=\"openPopup('https://portal.stf.jus.br/jurisprudencia/obterInteiroTeor.asp?numero=19845&classe=Rcl-AgR')\" class=\"urls\">Rcl 19845 AgR</a> (1ªT), <a onclick=\"openPopup('https://portal.stf.jus.br/jurisprudencia/obterInteiroTeor.asp?numero=20895&classe=Rcl-AgR')\" class=\"urls\">Rcl 20895 AgR</a> (2ªT), <a onclick=\"openPopup('https://portal.stf.jus.br/jurisprudencia/obterInteiroTeor.asp?numero=22129&classe=Rcl-AgR')\" class=\"urls\">Rcl 22129 AgR</a> (1ªT), <a onclick=\"openPopup('https://portal.stf.jus.br/jurisprudencia/obterInteiroTeor.asp?numero=27554&classe=Rcl-AgR')\" class=\"urls\">Rcl 27554 AgR</a> (2ªT), <a onclick=\"openPopup('https://portal.stf.jus.br/jurisprudencia/obterInteiroTeor.asp?numero=30882&classe=Rcl-AgR')\" class=\"urls\">Rcl 30882 AgR</a> (2ªT), <a onclick=\"openPopup('https://portal.stf.jus.br/jurisprudencia/obterInteiroTeor.asp?numero=30880&classe=Rcl-AgR')\" class=\"urls\">Rcl 30880 AgR</a> (2ªT), <a onclick=\"openPopup('https://portal.stf.jus.br/jurisprudencia/obterInteiroTeor.asp?numero=33578&classe=Rcl-AgR')\" class=\"urls\">Rcl 33578 AgR</a> (2ªT). \n(COMPROVAÇÃO, NEGLIGÊNCIA, ADMINISTRAÇÃO PÚBLICA, EMPREGADO TERCEIRIZADO, PROVA, NEXO DE CAUSALIDADE, CONDUTA, DANO, TRABALHADOR)\n<a onclick=\"openPopup('https://portal.stf.jus.br/jurisprudencia/obterInteiroTeor.asp?numero=30560&classe=Rcl-AgR')\" class=\"urls\">Rcl 30560 AgR</a> (1ªT), <a onclick=\"openPopup('https://portal.stf.jus.br/jurisprudencia/obterInteiroTeor.asp?numero=34039&classe=Rcl-AgR')\" class=\"urls\">Rcl 34039 AgR</a> (1ªT), <a onclick=\"openPopup('https://portal.stf.jus.br/jurisprudencia/obterInteiroTeor.asp?numero=38016&classe=Rcl-AgR')\" class=\"urls\">Rcl 38016 AgR</a> (1ªT), <a onclick=\"openPopup('https://portal.stf.jus.br/jurisprudencia/obterInteiroTeor.asp?numero=36836&classe=Rcl-ED-AgR')\" class=\"urls\">Rcl 36836 ED-AgR</a> (1ªT), <a onclick=\"openPopup('https://portal.stf.jus.br/jurisprudencia/obterInteiroTeor.asp?numero=39844&classe=Rcl-AgR')\" class=\"urls\">Rcl 39844 AgR</a> (1ªT), <a onclick=\"openPopup('https://portal.stf.jus.br/jurisprudencia/obterInteiroTeor.asp?numero=39978&classe=Rcl-AgR')\" class=\"urls\">Rcl 39978 AgR</a> (1ªT). \n- Decisões monocráticas citadas:\n(RESPONSABILIDADE SUBSIDIÁRIA, ADMINISTRAÇÃO PÚBLICA, INADIMPLEMENTO, EMPRESA PRESTADORA DE SERVIÇO, DISTRIBUIÇÃO, ÔNUS DA PROVA)\nRcl 14832 MC, Rcl 15385 MC, Rcl 15194.\n(RECLAMAÇÃO, REEXAME, FATO, PROVA)\nRcl 14048, Rcl 12634, Rcl 17831, Rcl 21162, Rcl 21495.\n(INTERPRETAÇÃO SISTEMÁTICA, PEDIDO)\nRcl 37203, Rcl 37298, Rcl 41513.\n(COMPROVAÇÃO, NEGLIGÊNCIA, ADMINISTRAÇÃO PÚBLICA, EMPREGADO TERCEIRIZADO, PROVA, NEXO DE CAUSALIDADE, CONDUTA, DANO, TRABALHADOR)\nRcl 37320.\n- Veja ADC 16 e RE 760931 do STF.\nNúmero de páginas: 28.\nAnálise: 02/03/2022, JSF.",
    "documental_assunto_texto": null,
    "documental_doutrina_texto": null,
    "documental_tese_tipo": null,
    "documental_tese_texto": null,
    "documental_tese_tema_texto": null,
    "dg_atualizado_em": "2023-10-04T14:44:52.853841",
    "externo_seq_objeto_incidente": 5966901,
    "old_seq_colac": null,
    "old_seq_repercussao_geral": null,
    "old_seq_sjur": 444522,
    "ods_onu": []
  }
}